<?xml version="1.0" standalone="yes"?>

<!-- Generated by BEAUTi v1.10.4 Prerelease #bc6cbd9                         -->
<!--       by Alexei J. Drummond, Andrew Rambaut and Marc A. Suchard         -->
<!--       Department of Computer Science, University of Auckland and        -->
<!--       Institute of Evolutionary Biology, University of Edinburgh        -->
<!--       David Geffen School of Medicine, University of California, Los Angeles-->
<!--       http://beast.community/                                           -->
<beast version="1.10.4">


	<!-- The list of taxa to be analysed (can also include dates/ages).          -->                                                             -->
	<!-- ntax=484                                                                 -->
	<taxa id="taxa">
		<taxon id="H5N1|2344b|EPI_ISL_603133|anseriformes|netherlands|2_1_1_1_1_1_1_1|2020-10-16">
			<date value="2020.7896174863388" direction="forwards" units="years"/>
		</taxon>
		<taxon id="H5N1|2344b|EPI_ISL_603134|anseriformes|netherlands|2_1_1_1_1_1_1_1|2020-10-16">
			<date value="2020.7896174863388" direction="forwards" units="years"/>
		</taxon>
		<taxon id="H5N1|2344b|EPI_ISL_603135|anseriformes|netherlands|2_1_1_1_1_1_1_1|2020-10-16">
			<date value="2020.7896174863388" direction="forwards" units="years"/>
		</taxon>
		<taxon id="H5N1|2344b|EPI_ISL_711055|galliformes|netherlands|2_1_1_1_1_1_1_1|2020-12-14">
			<date value="2020.950819672131" direction="forwards" units="years"/>
		</taxon>
		<taxon id="H5N1|2344b|EPI_ISL_632316|charadriiformes|netherlands|3_1_2_1_11_1_1_2|2020-11-01">
			<date value="2020.8333333333333" direction="forwards" units="years"/>
		</taxon>
		<taxon id="H5N1|2344b|EPI_ISL_5145223|galliformes|germany|2_1_1_1_1_1_1_1|2021-05-05">
			<date value="2021.3397260273973" direction="forwards" units="years"/>
		</taxon>
		<taxon id="H5N1|2344b|EPI_ISL_5804788|anseriformes|netherlands|1_1_2_1_1_1_1_1|2021-10-24">
			<date value="2021.8109589041096" direction="forwards" units="years"/>
		</taxon>
		<taxon id="H5N1|2344b|EPI_ISL_6596216|anseriformes|sweden|2_1_1_1_1_1_1_1|2021-11-02">
			<date value="2021.835616438356" direction="forwards" units="years"/>
		</taxon>
		<taxon id="H5N1|2344b|EPI_ISL_7049600|anseriformes|sweden|24_1_1_1_1_1_1_1|2021-11-05">
			<date value="2021.8438356164384" direction="forwards" units="years"/>
		</taxon>
		<taxon id="H5N1|2344b|EPI_ISL_7050532|passeriformes|sweden|25_1_1_1_1_1_1_1|2021-11-08">
			<date value="2021.8520547945207" direction="forwards" units="years"/>
		</taxon>
		<taxon id="H5N1|2344b|EPI_ISL_7267248|anseriformes|netherlands|2_1_1_1_1_1_1_1|2021-11-14">
			<date value="2021.868493150685" direction="forwards" units="years"/>
		</taxon>
		<taxon id="H5N1|2344b|EPI_ISL_7267254|anseriformes|netherlands|2_1_1_1_1_1_1_1|2021-11-23">
			<date value="2021.8931506849315" direction="forwards" units="years"/>
		</taxon>
		<taxon id="H5N1|2344b|EPI_ISL_7357590|anseriformes|croatia|1_1_2_1_1_1_1_1|2021-11-12">
			<date value="2021.86301369863" direction="forwards" units="years"/>
		</taxon>
		<taxon id="H5N1|2344b|EPI_ISL_7733644|galliformes|italy|14_6_1_1_1_1_1_5|2021-10-28">
			<date value="2021.8219178082193" direction="forwards" units="years"/>
		</taxon>
		<taxon id="H5N1|2344b|EPI_ISL_7778765|accipitriformes|finland|2_1_1_1_1_1_1_1|2021-07-01">
			<date value="2021.495890410959" direction="forwards" units="years"/>
		</taxon>
		<taxon id="H5N1|2344b|EPI_ISL_7778880|carnivora|estonia|2_1_1_1_1_1_1_1|2021-11-08">
			<date value="2021.8520547945207" direction="forwards" units="years"/>
		</taxon>
		<taxon id="H5N1|2344b|EPI_ISL_2652003|accipitriformes|sweden|2_1_1_1_1_1_1_1|2021-05-25">
			<date value="2021.3945205479451" direction="forwards" units="years"/>
		</taxon>
		<taxon id="H5N1|2344b|EPI_ISL_3135897|galliformes|hungary|2_1_1_1_1_1_1_1|2021-04-13">
			<date value="2021.2794520547945" direction="forwards" units="years"/>
		</taxon>
		<taxon id="H5N1|2344b|EPI_ISL_6507374|anseriformes|croatia|2_1_1_1_1_1_1_1|2021-11-12">
			<date value="2021.86301369863" direction="forwards" units="years"/>
		</taxon>
		<taxon id="H5N1|2344b|EPI_ISL_6600943|charadriiformes|sweden|2_1_1_1_1_1_1_1|2021-11-09">
			<date value="2021.854794520548" direction="forwards" units="years"/>
		</taxon>
		<taxon id="H5N1|2344b|EPI_ISL_6761005|galliformes|netherlands|14_1_1_1_1_1_1_1|2021-11-05">
			<date value="2021.8438356164384" direction="forwards" units="years"/>
		</taxon>
		<taxon id="H5N1|2344b|EPI_ISL_6761008|anseriformes|netherlands|14_1_1_1_1_1_1_1|2021-10-30">
			<date value="2021.827397260274" direction="forwards" units="years"/>
		</taxon>
		<taxon id="H5N1|2344b|EPI_ISL_6761013|anseriformes|netherlands|1_1_2_1_1_1_1_1|2021-11-02">
			<date value="2021.835616438356" direction="forwards" units="years"/>
		</taxon>
		<taxon id="H5N1|2344b|EPI_ISL_6761016|anseriformes|netherlands|1_1_2_1_1_1_1_1|2021-11-02">
			<date value="2021.835616438356" direction="forwards" units="years"/>
		</taxon>
		<taxon id="H5N1|2344b|EPI_ISL_6761022|anseriformes|netherlands|1_1_1_1_1_1_1_1|2021-11-09">
			<date value="2021.854794520548" direction="forwards" units="years"/>
		</taxon>
		<taxon id="H5N1|2344b|EPI_ISL_7055384|anseriformes|sweden|2_1_1_1_1_1_1_1|2021-11-17">
			<date value="2021.876712328767" direction="forwards" units="years"/>
		</taxon>
		<taxon id="H5N1|2344b|EPI_ISL_7683077|anseriformes|netherlands|1_1_2_1_1_1_1_1|2021-11-24">
			<date value="2021.8958904109588" direction="forwards" units="years"/>
		</taxon>
		<taxon id="H5N1|2344b|EPI_ISL_7683138|carnivora|netherlands|2_1_1_1_1_1_1_1|2021-12-03">
			<date value="2021.9205479452055" direction="forwards" units="years"/>
		</taxon>
		<taxon id="H5N1|2344b|EPI_ISL_7748188|anseriformes|germany|2_1_2_1_1_1_1_1|2021-10-14">
			<date value="2021.7835616438356" direction="forwards" units="years"/>
		</taxon>
		<taxon id="H5N1|2344b|EPI_ISL_7753152|anseriformes|germany|2_1_2_1_1_1_1_1|2021-10-14">
			<date value="2021.7835616438356" direction="forwards" units="years"/>
		</taxon>
		<taxon id="H5N1|2344b|EPI_ISL_7753251|anseriformes|germany|2_1_1_1_1_1_1_1|2021-10-19">
			<date value="2021.7972602739726" direction="forwards" units="years"/>
		</taxon>
		<taxon id="H5N1|2344b|EPI_ISL_7753272|accipitriformes|germany|2_1_1_1_1_1_1_1|2021-10-20">
			<date value="2021.8" direction="forwards" units="years"/>
		</taxon>
		<taxon id="H5N1|2344b|EPI_ISL_7952115|anseriformes|netherlands|1_1_2_1_10_1_1_5|2021-11-24">
			<date value="2021.8958904109588" direction="forwards" units="years"/>
		</taxon>
		<taxon id="H5N1|2344b|EPI_ISL_7952118|galliformes|netherlands|2_1_1_1_1_1_1_1|2021-12-16">
			<date value="2021.9561643835616" direction="forwards" units="years"/>
		</taxon>
		<taxon id="H5N1|2344b|EPI_ISL_6328001|anseriformes|netherlands|2_1_1_1_1_1_1_1|2021-10-19">
			<date value="2021.7972602739726" direction="forwards" units="years"/>
		</taxon>
		<taxon id="H5N1|2344b|EPI_ISL_7626514|anseriformes|czechia|2_1_1_1_1_1_1_1|2021-11-29">
			<date value="2021.9095890410958" direction="forwards" units="years"/>
		</taxon>
		<taxon id="H5N1|2344b|EPI_ISL_5463801|galliformes|russia|1_1_2_1_1_1_1_1|2021-09-30">
			<date value="2021.7452054794521" direction="forwards" units="years"/>
		</taxon>
		<taxon id="H5N1|2344b|EPI_ISL_5463800|galliformes|russia|1_1_2_1_1_1_1_1|2021-09-30">
			<date value="2021.7452054794521" direction="forwards" units="years"/>
		</taxon>
		<taxon id="H5N1|2344b|EPI_ISL_5463795|galliformes|russia|2_1_1_1_1_1_1_1|2021-10-06">
			<date value="2021.7616438356165" direction="forwards" units="years"/>
		</taxon>
		<taxon id="H5N1|2344b|EPI_ISL_5463803|anseriformes|russia|1_1_2_1_1_1_1_1|2021-09-30">
			<date value="2021.7452054794521" direction="forwards" units="years"/>
		</taxon>
		<taxon id="H5N1|2344b|EPI_ISL_5463802|anseriformes|russia|1_1_2_1_1_1_1_1|2021-09-30">
			<date value="2021.7452054794521" direction="forwards" units="years"/>
		</taxon>
		<taxon id="H5N1|2344b|EPI_ISL_5463799|anseriformes|russia|1_1_2_1_1_1_1_1|2021-09-30">
			<date value="2021.7452054794521" direction="forwards" units="years"/>
		</taxon>
		<taxon id="H5N1|2344b|EPI_ISL_5463798|anseriformes|russia|1_1_2_1_1_1_1_1|2021-09-30">
			<date value="2021.7452054794521" direction="forwards" units="years"/>
		</taxon>
		<taxon id="H5N1|2344b|EPI_ISL_5463797|anseriformes|russia|1_1_2_1_1_1_1_1|2021-09-30">
			<date value="2021.7452054794521" direction="forwards" units="years"/>
		</taxon>
		<taxon id="H5N1|2344b|EPI_ISL_8377056|pelecaniformes|france|2_1_1_1_1_1_1_1|2021-12-15">
			<date value="2021.9534246575342" direction="forwards" units="years"/>
		</taxon>
		<taxon id="H5N1|2344b|EPI_ISL_8377254|pelecaniformes|france|14_6_1_1_1_1_1_5|2021-12-03">
			<date value="2021.9205479452055" direction="forwards" units="years"/>
		</taxon>
		<taxon id="H5N1|2344b|EPI_ISL_8377417|galliformes|france|1_1_2_1_1_1_1_1|2021-11-25">
			<date value="2021.8986301369864" direction="forwards" units="years"/>
		</taxon>
		<taxon id="H5N1|2344b|EPI_ISL_8377418|anseriformes|france|1_1_2_1_1_1_1_1|2021-11-25">
			<date value="2021.8986301369864" direction="forwards" units="years"/>
		</taxon>
		<taxon id="H5N1|2344b|EPI_ISL_9261742|charadriiformes|netherlands|2_1_1_1_1_1_1_1|2022-01-06">
			<date value="2022.013698630137" direction="forwards" units="years"/>
		</taxon>
		<taxon id="H5N1|2344b|EPI_ISL_9261744|anseriformes|netherlands|2_1_2_1_1_1_1_1|2022-01-11">
			<date value="2022.027397260274" direction="forwards" units="years"/>
		</taxon>
		<taxon id="H5N1|2344b|EPI_ISL_10220427|carnivora|netherlands|2_1_1_1_1_1_1_1|2022-02-07">
			<date value="2022.1013698630136" direction="forwards" units="years"/>
		</taxon>
		<taxon id="H5N1|2344b|EPI_ISL_10261376|columbiformes|germany|2_1_1_1_10_1_1_1|2022-01-24">
			<date value="2022.0630136986301" direction="forwards" units="years"/>
		</taxon>
		<taxon id="H5N1|2344b|EPI_ISL_10347326|strigiformes|germany|2_1_1_1_10_1_1_1|2021-12-28">
			<date value="2021.9890410958903" direction="forwards" units="years"/>
		</taxon>
		<taxon id="H5N1|2344b|EPI_ISL_10724257|charadriiformes|netherlands|2_1_1_1_10_1_1_1|2021-12-23">
			<date value="2021.9753424657533" direction="forwards" units="years"/>
		</taxon>
		<taxon id="H5N1|2344b|EPI_ISL_12325210|galliformes|czechia|1_1_3_1_9_1_1_1|2022-02-09">
			<date value="2022.1068493150685" direction="forwards" units="years"/>
		</taxon>
		<taxon id="H5N1|2344b|EPI_ISL_13026245|anseriformes|luxembourg|2_1_1_1_1_1_1_1|2022-01-17">
			<date value="2022.0438356164384" direction="forwards" units="years"/>
		</taxon>
		<taxon id="H5N1|2344b|EPI_ISL_13026246|anseriformes|luxembourg|1_1_2_1_1_1_1_1|2022-02-04">
			<date value="2022.0931506849315" direction="forwards" units="years"/>
		</taxon>
		<taxon id="H5N1|2344b|EPI_ISL_13246657|galliformes|iceland|2_1_1_1_1_1_1_1|2022-04-14">
			<date value="2022.282191780822" direction="forwards" units="years"/>
		</taxon>
		<taxon id="H5N1|2344b|EPI_ISL_13955171|galliformes|czechia|14_6_1_1_1_1_1_5|2022-02-04">
			<date value="2022.0931506849315" direction="forwards" units="years"/>
		</taxon>
		<taxon id="H5N1|2344b|EPI_ISL_14811929|suliformes|sweden|2_1_1_1_1_1_1_1|2022-06-15">
			<date value="2022.4520547945206" direction="forwards" units="years"/>
		</taxon>
		<taxon id="H5N1|2344b|EPI_ISL_15581789|anseriformes|netherlands|2_1_2_1_1_1_1_1|2022-10-12">
			<date value="2022.7780821917809" direction="forwards" units="years"/>
		</taxon>
		<taxon id="H5N1|2344b|EPI_ISL_15585857|galliformes|united_kingdom|1_1_2_1_9_1_1_1|2022-09-18">
			<date value="2022.7123287671234" direction="forwards" units="years"/>
		</taxon>
		<taxon id="H5N1|2344b|EPI_ISL_15925880|anseriformes|netherlands|14_1_3_1_1_1_1_1|2022-11-09">
			<date value="2022.854794520548" direction="forwards" units="years"/>
		</taxon>
		<taxon id="H5N1|2344b|EPI_ISL_15925883|anseriformes|netherlands|14_1_3_1_1_1_1_1|2022-11-01">
			<date value="2022.8328767123287" direction="forwards" units="years"/>
		</taxon>
		<taxon id="H5N1|2344b|EPI_ISL_15925884|suliformes|netherlands|2_1_18_1_1_1_1_1|2022-11-11">
			<date value="2022.8602739726027" direction="forwards" units="years"/>
		</taxon>
		<taxon id="H5N1|2344b|EPI_ISL_15925885|charadriiformes|netherlands|14_1_3_1_1_1_1_1|2022-11-11">
			<date value="2022.8602739726027" direction="forwards" units="years"/>
		</taxon>
		<taxon id="H5N1|2344b|EPI_ISL_16040744|anseriformes|netherlands|14_1_3_1_1_1_1_1|2022-11-21">
			<date value="2022.8876712328768" direction="forwards" units="years"/>
		</taxon>
		<taxon id="H5N1|2344b|EPI_ISL_16098026|charadriiformes|germany|1_1_2_1_1_1_1_1|2022-07-14">
			<date value="2022.531506849315" direction="forwards" units="years"/>
		</taxon>
		<taxon id="H5N1|2344b|EPI_ISL_8799314|charadriiformes|netherlands|2_1_1_1_10_1_1_1|2021-12-17">
			<date value="2021.958904109589" direction="forwards" units="years"/>
		</taxon>
		<taxon id="H5N1|2344b|EPI_ISL_8799317|charadriiformes|netherlands|1_1_1_1_1_1_1_1|2021-12-24">
			<date value="2021.978082191781" direction="forwards" units="years"/>
		</taxon>
		<taxon id="H5N1|2344b|EPI_ISL_8799318|accipitriformes|netherlands|1_1_2_1_1_1_1_1|2021-12-26">
			<date value="2021.9835616438356" direction="forwards" units="years"/>
		</taxon>
		<taxon id="H5N1|2344b|EPI_ISL_8799552|primates|united_kingdom|2_1_1_1_1_1_1_1|2021-12-26">
			<date value="2021.9835616438356" direction="forwards" units="years"/>
		</taxon>
		<taxon id="H5N1|2344b|EPI_ISL_9012572|galliformes|united_kingdom|14_1_1_1_1_1_1_1|2021-10-27">
			<date value="2021.8191780821917" direction="forwards" units="years"/>
		</taxon>
		<taxon id="H5N1|2344b|EPI_ISL_9012580|anseriformes|netherlands|2_1_1_1_1_1_1_1|2021-12-27">
			<date value="2021.986301369863" direction="forwards" units="years"/>
		</taxon>
		<taxon id="H5N1|2344b|EPI_ISL_9012618|galliformes|united_kingdom|14_1_1_1_1_1_1_1|2021-10-30">
			<date value="2021.827397260274" direction="forwards" units="years"/>
		</taxon>
		<taxon id="H5N1|2344b|EPI_ISL_9221430|accipitriformes|netherlands|14_1_1_1_1_1_1_1|2021-12-27">
			<date value="2021.986301369863" direction="forwards" units="years"/>
		</taxon>
		<taxon id="H5N1|2344b|EPI_ISL_9377021|anseriformes|france|14_1_1_1_9_1_1_1|2021-12-23">
			<date value="2021.9753424657533" direction="forwards" units="years"/>
		</taxon>
		<taxon id="H5N1|2344b|EPI_ISL_11007527|galliformes|moldova|14_6_1_1_1_1_1_5|2022-01-03">
			<date value="2022.0054794520547" direction="forwards" units="years"/>
		</taxon>
		<taxon id="H5N1|2344b|EPI_ISL_11007535|anseriformes|slovenia|2_1_1_1_1_1_1_1|2022-01-03">
			<date value="2022.0054794520547" direction="forwards" units="years"/>
		</taxon>
		<taxon id="H5N1|2344b|EPI_ISL_11007722|galliformes|bulgaria|14_6_1_1_1_1_1_5|2021-11-23">
			<date value="2021.8931506849315" direction="forwards" units="years"/>
		</taxon>
		<taxon id="H5N1|2344b|EPI_ISL_11327090|galliformes|czechia|2_1_1_1_1_1_1_1|2022-01-03">
			<date value="2022.0054794520547" direction="forwards" units="years"/>
		</taxon>
		<taxon id="H5N1|2344b|EPI_ISL_11560235|anseriformes|netherlands|1_1_2_1_1_1_1_1|2022-03-03">
			<date value="2022.1671232876713" direction="forwards" units="years"/>
		</taxon>
		<taxon id="H5N1|2344b|EPI_ISL_11560325|charadriiformes|netherlands|1_1_18_1_1_1_1_1|2022-03-15">
			<date value="2022.2" direction="forwards" units="years"/>
		</taxon>
		<taxon id="H5N1|2344b|EPI_ISL_11798571|accipitriformes|denmark|2_1_1_1_1_1_1_1|2021-10-25">
			<date value="2021.813698630137" direction="forwards" units="years"/>
		</taxon>
		<taxon id="H5N1|2344b|EPI_ISL_11798572|anseriformes|denmark|1_1_1_1_1_1_1_1|2021-10-13">
			<date value="2021.7808219178082" direction="forwards" units="years"/>
		</taxon>
		<taxon id="H5N1|2344b|EPI_ISL_11798577|pelecaniformes|denmark|2_1_1_1_1_1_1_1|2021-10-28">
			<date value="2021.8219178082193" direction="forwards" units="years"/>
		</taxon>
		<taxon id="H5N1|2344b|EPI_ISL_12150666|anseriformes|czechia|2_1_1_1_1_1_1_1|2021-12-18">
			<date value="2021.9616438356165" direction="forwards" units="years"/>
		</taxon>
		<taxon id="H5N1|2344b|EPI_ISL_12223688|pelecaniformes|czechia|11_1_3_1_9_1_1_5|2021-12-18">
			<date value="2021.9616438356165" direction="forwards" units="years"/>
		</taxon>
		<taxon id="H5N1|2344b|EPI_ISL_13370517|anseriformes|united_kingdom|2_1_1_1_1_1_1_1|2021-12-04">
			<date value="2021.9232876712329" direction="forwards" units="years"/>
		</taxon>
		<taxon id="H5N1|2344b|EPI_ISL_13370630|accipitriformes|united_kingdom|2_1_1_1_1_1_1_1|2021-12-31">
			<date value="2021.9972602739726" direction="forwards" units="years"/>
		</taxon>
		<taxon id="H5N1|2344b|EPI_ISL_13370693|anseriformes|isle_of_man|2_1_1_1_1_1_1_1|2022-01-14">
			<date value="2022.035616438356" direction="forwards" units="years"/>
		</taxon>
		<taxon id="H5N1|2344b|EPI_ISL_13370896|anseriformes|jersey|2_1_1_1_1_1_1_1|2022-02-22">
			<date value="2022.1424657534246" direction="forwards" units="years"/>
		</taxon>
		<taxon id="H5N1|2344b|EPI_ISL_14493135|ciconiiformes|netherlands|1_1_1_1_1_1_1_1|2022-06-03">
			<date value="2022.4191780821918" direction="forwards" units="years"/>
		</taxon>
		<taxon id="H5N1|2344b|EPI_ISL_14702899|suliformes|france|2_1_1_1_1_1_1_1|2022-07-13">
			<date value="2022.5287671232877" direction="forwards" units="years"/>
		</taxon>
		<taxon id="H5N1|2344b|EPI_ISL_14841913|anseriformes|france|2_1_4_1_9_1_1_1|2022-07-06">
			<date value="2022.509589041096" direction="forwards" units="years"/>
		</taxon>
		<taxon id="H5N1|2344b|EPI_ISL_15022831|anseriformes|lithuania|2_1_1_1_1_1_1_1|2022-02-09">
			<date value="2022.1068493150685" direction="forwards" units="years"/>
		</taxon>
		<taxon id="H5N1|2344b|EPI_ISL_15234356|anseriformes|france|1_1_2_1_1_1_1_1|2022-06-29">
			<date value="2022.490410958904" direction="forwards" units="years"/>
		</taxon>
		<taxon id="H5N1|2344b|EPI_ISL_15234359|anseriformes|france|2_1_1_1_1_1_1_1|2022-02-23">
			<date value="2022.145205479452" direction="forwards" units="years"/>
		</taxon>
		<taxon id="H5N1|2344b|EPI_ISL_15542438|primates|spain|1_1_2_1_1_1_1_1|2022-09-23">
			<date value="2022.7260273972602" direction="forwards" units="years"/>
		</taxon>
		<taxon id="H5N1|2344b|EPI_ISL_15579543|anseriformes|netherlands|1_1_2_1_11_1_1_1|2022-10-01">
			<date value="2022.7479452054795" direction="forwards" units="years"/>
		</taxon>
		<taxon id="H5N1|2344b|EPI_ISL_15857841|anseriformes|italy|1_1_2_1_9_1_1_5|2022-11-07">
			<date value="2022.849315068493" direction="forwards" units="years"/>
		</taxon>
		<taxon id="H5N1|2344b|EPI_ISL_15857956|anseriformes|italy|1_1_2_1_1_1_1_1|2022-10-19">
			<date value="2022.7972602739726" direction="forwards" units="years"/>
		</taxon>
		<taxon id="H5N1|2344b|EPI_ISL_15857992|galliformes|france|14_1_3_1_1_1_1_1|2022-11-08">
			<date value="2022.8520547945207" direction="forwards" units="years"/>
		</taxon>
		<taxon id="H5N1|2344b|EPI_ISL_15909904|anseriformes|netherlands|14_1_3_1_1_1_1_1|2022-10-31">
			<date value="2022.8301369863013" direction="forwards" units="years"/>
		</taxon>
		<taxon id="H5N1|2344b|EPI_ISL_16115054|accipitriformes|denmark|2_1_2_1_1_1_1_1|2022-08-30">
			<date value="2022.6602739726027" direction="forwards" units="years"/>
		</taxon>
		<taxon id="H5N1|2344b|EPI_ISL_16196757|anseriformes|cyprus|1_1_2_1_1_1_1_1|2022-11-28">
			<date value="2022.9068493150685" direction="forwards" units="years"/>
		</taxon>
		<taxon id="H5N1|2344b|EPI_ISL_9603916|anseriformes|czechia|2_1_1_1_1_1_1_1|2021-11-12">
			<date value="2021.86301369863" direction="forwards" units="years"/>
		</taxon>
		<taxon id="H5N1|2344b|EPI_ISL_9603920|anseriformes|czechia|2_1_1_1_1_1_1_1|2021-11-15">
			<date value="2021.8712328767124" direction="forwards" units="years"/>
		</taxon>
		<taxon id="H5N1|2344b|EPI_ISL_9603927|anseriformes|czechia|2_1_1_1_1_1_1_1|2021-12-20">
			<date value="2021.9671232876713" direction="forwards" units="years"/>
		</taxon>
		<taxon id="H5N1|2344b|EPI_ISL_9603931|galliformes|czechia|2_1_1_1_1_1_1_1|2021-12-25">
			<date value="2021.9808219178083" direction="forwards" units="years"/>
		</taxon>
		<taxon id="H5N1|2344b|EPI_ISL_9603939|galliformes|czechia|2_1_1_1_1_1_1_1|2021-12-25">
			<date value="2021.9808219178083" direction="forwards" units="years"/>
		</taxon>
		<taxon id="H5N1|2344b|EPI_ISL_9616212|charadriiformes|netherlands|2_1_1_1_10_1_1_1|2022-01-06">
			<date value="2022.013698630137" direction="forwards" units="years"/>
		</taxon>
		<taxon id="H5N1|2344b|EPI_ISL_9616271|carnivora|netherlands|1_1_2_1_1_1_1_1|2022-01-31">
			<date value="2022.0821917808219" direction="forwards" units="years"/>
		</taxon>
		<taxon id="H5N1|2344b|EPI_ISL_11259265|falconiformes|ireland|2_1_1_1_10_1_1_1|2022-01-05">
			<date value="2022.0109589041097" direction="forwards" units="years"/>
		</taxon>
		<taxon id="H5N1|2344b|EPI_ISL_11259276|falconiformes|ireland|1_1_2_1_1_1_1_1|2021-11-10">
			<date value="2021.8575342465754" direction="forwards" units="years"/>
		</taxon>
		<taxon id="H5N1|2344b|EPI_ISL_11561592|galliformes|united_kingdom|2_1_1_1_10_1_1_1|2022-02-20">
			<date value="2022.13698630137" direction="forwards" units="years"/>
		</taxon>
		<taxon id="H5N1|2344b|EPI_ISL_11725869|anseriformes|germany|2_1_1_1_1_1_1_1|2021-11-02">
			<date value="2021.835616438356" direction="forwards" units="years"/>
		</taxon>
		<taxon id="H5N1|2344b|EPI_ISL_11725988|galliformes|germany|2_1_1_1_1_1_1_1|2021-11-02">
			<date value="2021.835616438356" direction="forwards" units="years"/>
		</taxon>
		<taxon id="H5N1|2344b|EPI_ISL_11922816|anseriformes|italy|2_1_1_1_1_1_1_1|2022-02-01">
			<date value="2022.0849315068492" direction="forwards" units="years"/>
		</taxon>
		<taxon id="H5N1|2344b|EPI_ISL_11922819|galliformes|italy|14_6_1_1_1_1_1_5|2022-02-10">
			<date value="2022.109589041096" direction="forwards" units="years"/>
		</taxon>
		<taxon id="H5N1|2344b|EPI_ISL_12139999|anseriformes|czechia|2_1_1_1_1_1_1_1|2022-01-10">
			<date value="2022.0246575342467" direction="forwards" units="years"/>
		</taxon>
		<taxon id="H5N1|2344b|EPI_ISL_12324302|anseriformes|czechia|1_1_3_1_9_1_1_1|2022-02-09">
			<date value="2022.1068493150685" direction="forwards" units="years"/>
		</taxon>
		<taxon id="H5N1|2344b|EPI_ISL_13245602|accipitriformes|iceland|2_1_1_1_1_1_1_1|2021-10-25">
			<date value="2021.813698630137" direction="forwards" units="years"/>
		</taxon>
		<taxon id="H5N1|2344b|EPI_ISL_13429295|charadriiformes|netherlands|1_1_2_1_1_1_1_1|2022-06-04">
			<date value="2022.4219178082192" direction="forwards" units="years"/>
		</taxon>
		<taxon id="H5N1|2344b|EPI_ISL_13519451|charadriiformes|france|1_1_4_1_4_1_1_4|2022-05-11">
			<date value="2022.3561643835617" direction="forwards" units="years"/>
		</taxon>
		<taxon id="H5N1|2344b|EPI_ISL_13782459|galliformes|united_kingdom|1_1_4_1_4_1_1_4|2022-06-15">
			<date value="2022.4520547945206" direction="forwards" units="years"/>
		</taxon>
		<taxon id="H5N1|2344b|EPI_ISL_14391865|accipitriformes|belgium|2_1_1_1_10_1_1_1|2022-02-20">
			<date value="2022.13698630137" direction="forwards" units="years"/>
		</taxon>
		<taxon id="H5N1|2344b|EPI_ISL_14573037|charadriiformes|germany|1_1_2_1_1_1_1_1|2022-05-31">
			<date value="2022.4109589041095" direction="forwards" units="years"/>
		</taxon>
		<taxon id="H5N1|2344b|EPI_ISL_14573045|charadriiformes|germany|1_1_2_1_1_1_1_1|2022-06-07">
			<date value="2022.4301369863015" direction="forwards" units="years"/>
		</taxon>
		<taxon id="H5N1|2344b|EPI_ISL_14760737|galliformes|italy|2_1_1_1_1_1_1_1|2021-12-13">
			<date value="2021.9479452054795" direction="forwards" units="years"/>
		</taxon>
		<taxon id="H5N1|2344b|EPI_ISL_14760946|galliformes|italy|14_6_1_1_1_1_1_5|2021-12-21">
			<date value="2021.9698630136986" direction="forwards" units="years"/>
		</taxon>
		<taxon id="H5N1|2344b|EPI_ISL_14761165|galliformes|italy|2_1_1_1_1_1_1_1|2021-12-27">
			<date value="2021.986301369863" direction="forwards" units="years"/>
		</taxon>
		<taxon id="H5N1|2344b|EPI_ISL_15518266|galliformes|finland|14_1_1_1_1_1_1_1|2021-10-01">
			<date value="2021.7479452054795" direction="forwards" units="years"/>
		</taxon>
		<taxon id="H5N1|2344b|EPI_ISL_15518267|strigiformes|finland|14_1_1_1_1_1_1_1|2021-10-01">
			<date value="2021.7479452054795" direction="forwards" units="years"/>
		</taxon>
		<taxon id="H5N1|2344b|EPI_ISL_15518269|carnivora|finland|14_1_1_1_1_1_1_1|2022-02-01">
			<date value="2022.0849315068492" direction="forwards" units="years"/>
		</taxon>
		<taxon id="H5N1|2344b|EPI_ISL_16096042|charadriiformes|germany|2_1_1_1_1_1_1_1|2022-02-07">
			<date value="2022.1013698630136" direction="forwards" units="years"/>
		</taxon>
		<taxon id="H5N1|2344b|EPI_ISL_16113229|charadriiformes|denmark|1_1_2_1_1_1_1_1|2022-06-17">
			<date value="2022.4575342465753" direction="forwards" units="years"/>
		</taxon>
		<taxon id="H5N1|2344b|EPI_ISL_11922815|anseriformes|italy|14_6_1_1_1_1_1_5|2021-12-08">
			<date value="2021.9342465753425" direction="forwards" units="years"/>
		</taxon>
		<taxon id="H5N1|2344b|EPI_ISL_15957998|galliformes|united_kingdom|13_1_2_1_1_1_1_1|2022-11-15">
			<date value="2022.8712328767124" direction="forwards" units="years"/>
		</taxon>
		<taxon id="H5N1|2344b|EPI_ISL_15957899|galliformes|united_kingdom|13_1_2_1_1_1_1_1|2022-11-06">
			<date value="2022.8465753424657" direction="forwards" units="years"/>
		</taxon>
		<taxon id="H5N1|2344b|EPI_ISL_8416806|galliformes|portugal|1_1_2_1_1_1_1_1|2021-12-05">
			<date value="2021.9260273972602" direction="forwards" units="years"/>
		</taxon>
		<taxon id="H5N1|2344b|EPI_ISL_11259262|passeriformes|ireland|2_1_1_1_1_1_1_1|2021-12-08">
			<date value="2021.9342465753425" direction="forwards" units="years"/>
		</taxon>
		<taxon id="H5N1|2344b|EPI_ISL_12471662|pelecaniformes|greece|1_1_2_1_1_1_1_1|2022-03-10">
			<date value="2022.186301369863" direction="forwards" units="years"/>
		</taxon>
		<taxon id="H5N1|2344b|EPI_ISL_12471660|pelecaniformes|greece|1_1_2_1_1_1_1_1|2022-03-10">
			<date value="2022.186301369863" direction="forwards" units="years"/>
		</taxon>
		<taxon id="H5N1|2344b|EPI_ISL_16838580|pelecaniformes|russia|2_1_1_1_1_1_1_1|2021-06-29">
			<date value="2021.490410958904" direction="forwards" units="years"/>
		</taxon>
		<taxon id="H5N1|2344b|EPI_ISL_10497305|charadriiformes|germany|2_1_1_1_10_1_1_1|2022-01-25">
			<date value="2022.0657534246575" direction="forwards" units="years"/>
		</taxon>
		<taxon id="H5N1|2344b|EPI_ISL_14810369|cetacea|sweden|2_1_1_1_1_1_1_1|2022-06-29">
			<date value="2022.490410958904" direction="forwards" units="years"/>
		</taxon>
		<taxon id="H5N1|2344b|EPI_ISL_10993196|charadriiformes|netherlands|2_1_1_1_1_1_1_1|2022-01-29">
			<date value="2022.0767123287671" direction="forwards" units="years"/>
		</taxon>
		<taxon id="H5N1|2344b|EPI_ISL_15957728|galliformes|united_kingdom|1_1_2_1_1_1_1_1|2022-10-28">
			<date value="2022.8219178082193" direction="forwards" units="years"/>
		</taxon>
		<taxon id="H5N1|2344b|EPI_ISL_11922809|galliformes|poland|1_1_1_1_1_1_1_1|2022-02-18">
			<date value="2022.131506849315" direction="forwards" units="years"/>
		</taxon>
		<taxon id="H5N1|2344b|EPI_ISL_11922808|anseriformes|poland|11_1_3_1_9_1_1_5|2022-03-02">
			<date value="2022.164383561644" direction="forwards" units="years"/>
		</taxon>
		<taxon id="H5N1|2344b|EPI_ISL_14933724|anseriformes|france|1_1_3_1_1_1_1_1|2022-08-24">
			<date value="2022.6438356164383" direction="forwards" units="years"/>
		</taxon>
		<taxon id="H5N1|2344b|EPI_ISL_16838577|anseriformes|russia|2_1_1_1_1_1_1_1|2021-09-14">
			<date value="2021.7013698630137" direction="forwards" units="years"/>
		</taxon>
		<taxon id="H5N1|2344b|EPI_ISL_10497306|accipitriformes|germany|2_1_1_1_10_1_1_1|2022-02-11">
			<date value="2022.1123287671232" direction="forwards" units="years"/>
		</taxon>
		<taxon id="H5N1|2344b|EPI_ISL_16113366|accipitriformes|denmark|1_1_2_1_1_1_1_1|2022-06-11">
			<date value="2022.441095890411" direction="forwards" units="years"/>
		</taxon>
		<taxon id="H5N1|2344b|EPI_ISL_16113242|strigiformes|denmark|1_1_2_1_1_1_1_1|2022-06-08">
			<date value="2022.4328767123288" direction="forwards" units="years"/>
		</taxon>
		<taxon id="H5N1|2344b|EPI_ISL_8515483|pelecaniformes|czechia|11_1_3_1_9_1_1_5|2021-11-28">
			<date value="2021.9068493150685" direction="forwards" units="years"/>
		</taxon>
		<taxon id="H5N1|2344b|EPI_ISL_8515481|pelecaniformes|czechia|11_1_3_1_9_1_1_5|2021-11-28">
			<date value="2021.9068493150685" direction="forwards" units="years"/>
		</taxon>
		<taxon id="H5N1|2344b|EPI_ISL_8515482|pelecaniformes|czechia|11_1_3_1_9_1_1_5|2021-11-28">
			<date value="2021.9068493150685" direction="forwards" units="years"/>
		</taxon>
		<taxon id="H5N1|2344b|EPI_ISL_16384159|sphenisciformes|united_kingdom|14_1_3_1_1_1_1_1|2022-12-04">
			<date value="2022.9232876712329" direction="forwards" units="years"/>
		</taxon>
		<taxon id="H5N1|2344b|EPI_ISL_16384184|galliformes|united_kingdom|1_1_2_1_1_1_1_1|2022-12-06">
			<date value="2022.9287671232876" direction="forwards" units="years"/>
		</taxon>
		<taxon id="H5N1|2344b|EPI_ISL_16560282|anseriformes|sweden|1_1_2_1_1_1_1_1|2022-12-17">
			<date value="2022.958904109589" direction="forwards" units="years"/>
		</taxon>
		<taxon id="H5N1|2344b|EPI_ISL_16613711|galliformes|czechia|14_6_1_1_1_1_1_5|2022-12-30">
			<date value="2022.9945205479453" direction="forwards" units="years"/>
		</taxon>
		<taxon id="H5N1|2344b|EPI_ISL_16638696|galliformes|czechia|14_6_1_1_1_1_1_5|2023-01-11">
			<date value="2023.027397260274" direction="forwards" units="years"/>
		</taxon>
		<taxon id="H5N1|2344b|EPI_ISL_16740904|anseriformes|france|1_1_2_1_1_1_1_1|2022-12-01">
			<date value="2022.9150684931508" direction="forwards" units="years"/>
		</taxon>
		<taxon id="H5N1|2344b|EPI_ISL_16811181|anseriformes|united_kingdom|14_1_3_1_1_1_1_1|2023-01-03">
			<date value="2023.0054794520547" direction="forwards" units="years"/>
		</taxon>
		<taxon id="H5N1|2344b|EPI_ISL_16811193|galliformes|united_kingdom|14_1_3_1_1_1_1_1|2023-01-11">
			<date value="2023.027397260274" direction="forwards" units="years"/>
		</taxon>
		<taxon id="H5N1|2344b|EPI_ISL_16896605|charadriiformes|sweden|1_1_2_1_1_1_1_1|2023-01-19">
			<date value="2023.0493150684931" direction="forwards" units="years"/>
		</taxon>
		<taxon id="H5N1|2344b|EPI_ISL_16905050|anseriformes|croatia|1_1_2_1_1_1_1_1|2023-01-09">
			<date value="2023.021917808219" direction="forwards" units="years"/>
		</taxon>
		<taxon id="H5N1|2344b|EPI_ISL_16905051|anseriformes|croatia|1_1_2_1_1_1_1_1|2023-01-13">
			<date value="2023.0328767123287" direction="forwards" units="years"/>
		</taxon>
		<taxon id="H5N1|2344b|EPI_ISL_16937305|galliformes|czechia|14_6_1_1_1_1_1_5|2023-01-15">
			<date value="2023.0383561643835" direction="forwards" units="years"/>
		</taxon>
		<taxon id="H5N1|2344b|EPI_ISL_16937306|anseriformes|czechia|1_1_2_1_1_1_1_1|2023-01-16">
			<date value="2023.041095890411" direction="forwards" units="years"/>
		</taxon>
		<taxon id="H5N1|2344b|EPI_ISL_16937308|anseriformes|czechia|1_1_2_1_1_1_1_1|2023-01-16">
			<date value="2023.041095890411" direction="forwards" units="years"/>
		</taxon>
		<taxon id="H5N1|2344b|EPI_ISL_16937310|environment|czechia|1_1_2_1_1_1_1_1|2023-01-23">
			<date value="2023.0602739726028" direction="forwards" units="years"/>
		</taxon>
		<taxon id="H5N1|2344b|EPI_ISL_17015369|anseriformes|czechia|1_1_2_1_1_1_1_1|2023-02-16">
			<date value="2023.1260273972603" direction="forwards" units="years"/>
		</taxon>
		<taxon id="H5N1|2344b|EPI_ISL_17179652|galliformes|switzerland|1_1_2_1_1_1_1_1|2022-11-16">
			<date value="2022.8739726027397" direction="forwards" units="years"/>
		</taxon>
		<taxon id="H5N1|2344b|EPI_ISL_17179653|anseriformes|switzerland|1_1_2_1_1_1_1_1|2022-11-22">
			<date value="2022.890410958904" direction="forwards" units="years"/>
		</taxon>
		<taxon id="H5N1|2344b|EPI_ISL_17179654|pelecaniformes|switzerland|1_1_2_1_1_1_1_1|2023-01-17">
			<date value="2023.0438356164384" direction="forwards" units="years"/>
		</taxon>
		<taxon id="H5N1|2344b|EPI_ISL_17233302|carnivora|france|1_1_4_1_4_1_1_4|2023-02-10">
			<date value="2023.109589041096" direction="forwards" units="years"/>
		</taxon>
		<taxon id="H5N1|2344b|EPI_ISL_17277694|anseriformes|sweden|1_1_2_1_1_1_1_1|2023-03-13">
			<date value="2023.194520547945" direction="forwards" units="years"/>
		</taxon>
		<taxon id="H5N1|2344b|EPI_ISL_17470103|galliformes|czechia|1_1_2_1_1_1_1_1|2023-03-02">
			<date value="2023.164383561644" direction="forwards" units="years"/>
		</taxon>
		<taxon id="H5N1|2344b|EPI_ISL_17470108|charadriiformes|czechia|1_1_4_1_4_1_1_4|2023-04-04">
			<date value="2023.2547945205479" direction="forwards" units="years"/>
		</taxon>
		<taxon id="H5N1|2344b|EPI_ISL_17584752|galliformes|france|1_1_2_1_1_1_1_1|2021-11-28">
			<date value="2021.9068493150685" direction="forwards" units="years"/>
		</taxon>
		<taxon id="H5N1|2344b|EPI_ISL_17584810|charadriiformes|czechia|1_1_4_1_4_1_1_4|2023-04-03">
			<date value="2023.2520547945205" direction="forwards" units="years"/>
		</taxon>
		<taxon id="H5N1|2344b|EPI_ISL_17584813|charadriiformes|czechia|1_1_4_1_4_1_1_4|2023-04-11">
			<date value="2023.2739726027398" direction="forwards" units="years"/>
		</taxon>
		<taxon id="H5N1|2344b|EPI_ISL_17584818|charadriiformes|czechia|1_1_4_1_4_1_1_4|2023-04-12">
			<date value="2023.2767123287672" direction="forwards" units="years"/>
		</taxon>
		<taxon id="H5N1|2344b|EPI_ISL_17584827|charadriiformes|czechia|1_1_4_1_4_1_1_4|2023-04-20">
			<date value="2023.2986301369863" direction="forwards" units="years"/>
		</taxon>
		<taxon id="H5N1|2344b|EPI_ISL_17626167|charadriiformes|netherlands|1_1_4_1_4_1_1_4|2023-04-19">
			<date value="2023.295890410959" direction="forwards" units="years"/>
		</taxon>
		<taxon id="H5N1|2344b|EPI_ISL_17679793|anseriformes|slovenia|1_1_2_1_1_1_1_1|2023-01-31">
			<date value="2023.0821917808219" direction="forwards" units="years"/>
		</taxon>
		<taxon id="H5N1|2344b|EPI_ISL_17679802|anseriformes|france|14_1_3_1_1_1_1_1|2022-12-14">
			<date value="2022.9506849315069" direction="forwards" units="years"/>
		</taxon>
		<taxon id="H5N1|2344b|EPI_ISL_17679810|charadriiformes|france|1_1_4_1_4_1_1_4|2023-01-16">
			<date value="2023.041095890411" direction="forwards" units="years"/>
		</taxon>
		<taxon id="H5N1|2344b|EPI_ISL_17679815|galliformes|slovakia|1_1_2_1_1_1_1_1|2023-01-12">
			<date value="2023.0301369863014" direction="forwards" units="years"/>
		</taxon>
		<taxon id="H5N1|2344b|EPI_ISL_17679822|galliformes|slovakia|14_6_1_1_1_1_1_5|2023-01-27">
			<date value="2023.0712328767124" direction="forwards" units="years"/>
		</taxon>
		<taxon id="H5N1|2344b|EPI_ISL_17679824|galliformes|estonia|14_6_1_1_1_1_1_5|2023-02-15">
			<date value="2023.123287671233" direction="forwards" units="years"/>
		</taxon>
		<taxon id="H5N1|2344b|EPI_ISL_17716057|anseriformes|austria|1_1_2_1_1_1_1_1|2023-01-18">
			<date value="2023.0465753424658" direction="forwards" units="years"/>
		</taxon>
		<taxon id="H5N1|2344b|EPI_ISL_17716059|anseriformes|austria|1_1_2_1_1_1_1_1|2023-01-26">
			<date value="2023.0684931506848" direction="forwards" units="years"/>
		</taxon>
		<taxon id="H5N1|2344b|EPI_ISL_17716062|anseriformes|austria|1_1_2_1_1_1_1_1|2023-01-31">
			<date value="2023.0821917808219" direction="forwards" units="years"/>
		</taxon>
		<taxon id="H5N1|2344b|EPI_ISL_17716063|charadriiformes|austria|1_1_4_1_4_1_1_4|2023-02-28">
			<date value="2023.158904109589" direction="forwards" units="years"/>
		</taxon>
		<taxon id="H5N1|2344b|EPI_ISL_17716064|charadriiformes|austria|1_1_4_1_4_1_1_4|2023-03-08">
			<date value="2023.1808219178083" direction="forwards" units="years"/>
		</taxon>
		<taxon id="H5N1|2344b|EPI_ISL_17716088|accipitriformes|austria|1_1_4_1_4_1_1_4|2023-04-12">
			<date value="2023.2767123287672" direction="forwards" units="years"/>
		</taxon>
		<taxon id="H5N1|2344b|EPI_ISL_17719670|anseriformes|bosnia_and_herzegovina|2_1_1_1_1_1_5_1|2021-11-18">
			<date value="2021.8794520547945" direction="forwards" units="years"/>
		</taxon>
		<taxon id="H5N1|2344b|EPI_ISL_17731667|pelecaniformes|montenegro|2_1_2_1_1_1_1_1|2022-04-04">
			<date value="2022.2547945205479" direction="forwards" units="years"/>
		</taxon>
		<taxon id="H5N1|2344b|EPI_ISL_17736649|primates|united_kingdom|1_1_4_1_4_1_1_4|2023-05-06">
			<date value="2023.3424657534247" direction="forwards" units="years"/>
		</taxon>
		<taxon id="H5N1|2344b|EPI_ISL_17785726|anseriformes|austria|2_1_1_1_1_1_1_1|2022-01-14">
			<date value="2022.035616438356" direction="forwards" units="years"/>
		</taxon>
		<taxon id="H5N1|2344b|EPI_ISL_17785728|anseriformes|austria|2_1_1_1_1_1_1_1|2022-04-13">
			<date value="2022.2794520547945" direction="forwards" units="years"/>
		</taxon>
		<taxon id="H5N1|2344b|EPI_ISL_17785729|anseriformes|austria|2_1_1_1_1_1_1_1|2021-12-14">
			<date value="2021.9506849315069" direction="forwards" units="years"/>
		</taxon>
		<taxon id="H5N1|2344b|EPI_ISL_17785730|anseriformes|austria|1_1_2_1_1_1_1_17|2021-12-15">
			<date value="2021.9534246575342" direction="forwards" units="years"/>
		</taxon>
		<taxon id="H5N1|2344b|EPI_ISL_17785732|anseriformes|austria|2_1_1_1_1_1_1_1|2022-01-24">
			<date value="2022.0630136986301" direction="forwards" units="years"/>
		</taxon>
		<taxon id="H5N1|2344b|EPI_ISL_17859575|charadriiformes|sweden|1_1_4_1_4_1_1_4|2023-06-15">
			<date value="2023.4520547945206" direction="forwards" units="years"/>
		</taxon>
		<taxon id="H5N1|2344b|EPI_ISL_17880904|carnivora|germany|2_1_1_1_1_1_1_1|2023-01-09">
			<date value="2023.021917808219" direction="forwards" units="years"/>
		</taxon>
		<taxon id="H5N1|2344b|EPI_ISL_17880914|carnivora|germany|1_1_4_1_4_1_1_4|2023-03-29">
			<date value="2023.2383561643835" direction="forwards" units="years"/>
		</taxon>
		<taxon id="H5N1|2344b|EPI_ISL_17884625|falconiformes|czechia|1_1_4_1_4_1_1_4|2023-05-26">
			<date value="2023.3972602739725" direction="forwards" units="years"/>
		</taxon>
		<taxon id="H5N1|2344b|EPI_ISL_16574465|gruiformes|united_kingdom|14_1_3_1_1_1_1_1|2022-12-16">
			<date value="2022.9561643835616" direction="forwards" units="years"/>
		</taxon>
		<taxon id="H5N1|2344b|EPI_ISL_16574529|galliformes|isle_of_man|1_1_4_1_4_1_1_4|2022-12-26">
			<date value="2022.9835616438356" direction="forwards" units="years"/>
		</taxon>
		<taxon id="H5N1|2344b|EPI_ISL_16633463|anseriformes|sweden|1_1_2_1_1_1_1_1|2022-12-21">
			<date value="2022.9698630136986" direction="forwards" units="years"/>
		</taxon>
		<taxon id="H5N1|2344b|EPI_ISL_16833158|galliformes|luxembourg|1_1_2_1_1_1_1_1|2023-01-25">
			<date value="2023.0657534246575" direction="forwards" units="years"/>
		</taxon>
		<taxon id="H5N1|2344b|EPI_ISL_16956386|falconiformes|united_kingdom|13_1_2_1_1_1_1_1|2023-01-07">
			<date value="2023.0164383561644" direction="forwards" units="years"/>
		</taxon>
		<taxon id="H5N1|2344b|EPI_ISL_16969355|anseriformes|sweden|1_1_2_1_1_1_1_1|2023-01-10">
			<date value="2023.0246575342467" direction="forwards" units="years"/>
		</taxon>
		<taxon id="H5N1|2344b|EPI_ISL_16969356|anseriformes|sweden|13_1_2_1_1_1_1_1|2023-01-20">
			<date value="2023.0520547945205" direction="forwards" units="years"/>
		</taxon>
		<taxon id="H5N1|2344b|EPI_ISL_16969358|charadriiformes|sweden|14_1_3_1_1_1_1_1|2023-01-30">
			<date value="2023.0794520547945" direction="forwards" units="years"/>
		</taxon>
		<taxon id="H5N1|2344b|EPI_ISL_16984642|anseriformes|belgium|1_1_4_1_4_1_1_4|2023-01-02">
			<date value="2023.0027397260274" direction="forwards" units="years"/>
		</taxon>
		<taxon id="H5N1|2344b|EPI_ISL_16997293|galliformes|czechia|1_1_2_1_1_1_1_1|2022-12-09">
			<date value="2022.9369863013699" direction="forwards" units="years"/>
		</taxon>
		<taxon id="H5N1|2344b|EPI_ISL_16997759|anseriformes|czechia|1_1_2_1_1_1_1_1|2023-02-06">
			<date value="2023.0986301369862" direction="forwards" units="years"/>
		</taxon>
		<taxon id="H5N1|2344b|EPI_ISL_17033246|falconiformes|netherlands|1_1_2_1_1_1_1_1|2023-02-06">
			<date value="2023.0986301369862" direction="forwards" units="years"/>
		</taxon>
		<taxon id="H5N1|2344b|EPI_ISL_17164982|galliformes|czechia|14_6_1_1_1_1_1_5|2023-01-02">
			<date value="2023.0027397260274" direction="forwards" units="years"/>
		</taxon>
		<taxon id="H5N1|2344b|EPI_ISL_17164985|galliformes|czechia|14_6_1_1_1_1_1_5|2023-01-03">
			<date value="2023.0054794520547" direction="forwards" units="years"/>
		</taxon>
		<taxon id="H5N1|2344b|EPI_ISL_17164991|galliformes|czechia|1_1_2_1_1_1_1_1|2023-01-02">
			<date value="2023.0027397260274" direction="forwards" units="years"/>
		</taxon>
		<taxon id="H5N1|2344b|EPI_ISL_17164994|pelecaniformes|czechia|1_1_2_1_1_1_1_1|2023-02-21">
			<date value="2023.1397260273973" direction="forwards" units="years"/>
		</taxon>
		<taxon id="H5N1|2344b|EPI_ISL_17180382|charadriiformes|switzerland|1_1_2_1_1_1_1_1|2023-01-25">
			<date value="2023.0657534246575" direction="forwards" units="years"/>
		</taxon>
		<taxon id="H5N1|2344b|EPI_ISL_17233426|carnivora|france|1_1_2_1_1_1_1_1|2022-11-07">
			<date value="2022.849315068493" direction="forwards" units="years"/>
		</taxon>
		<taxon id="H5N1|2344b|EPI_ISL_17521022|anseriformes|united_kingdom|1_1_4_1_4_1_1_4|2023-03-30">
			<date value="2023.2410958904109" direction="forwards" units="years"/>
		</taxon>
		<taxon id="H5N1|2344b|EPI_ISL_17583227|carnivora|netherlands|1_1_2_1_1_1_1_1|2022-01-16">
			<date value="2022.041095890411" direction="forwards" units="years"/>
		</taxon>
		<taxon id="H5N1|2344b|EPI_ISL_17599455|falconiformes|belgium|1_1_4_1_4_1_1_4|2023-03-01">
			<date value="2023.1616438356164" direction="forwards" units="years"/>
		</taxon>
		<taxon id="H5N1|2344b|EPI_ISL_17656637|charadriiformes|luxembourg|1_1_4_1_4_1_1_4|2023-05-10">
			<date value="2023.3534246575343" direction="forwards" units="years"/>
		</taxon>
		<taxon id="H5N1|2344b|EPI_ISL_17672782|carnivora|netherlands|1_1_2_1_1_1_1_1|2023">
			<date value="2023.0" direction="forwards" units="years"/>
		</taxon>
		<taxon id="H5N1|2344b|EPI_ISL_17672824|strigiformes|sweden|1_1_2_1_1_1_1_1|2023-04-04">
			<date value="2023.2547945205479" direction="forwards" units="years"/>
		</taxon>
		<taxon id="H5N1|2344b|EPI_ISL_17673144|accipitriformes|sweden|1_1_2_1_1_1_1_1|2023-04-25">
			<date value="2023.3123287671233" direction="forwards" units="years"/>
		</taxon>
		<taxon id="H5N1|2344b|EPI_ISL_17693350|charadriiformes|germany|2_1_1_1_1_1_1_1|2022-10-13">
			<date value="2022.7808219178082" direction="forwards" units="years"/>
		</taxon>
		<taxon id="H5N1|2344b|EPI_ISL_17710026|anseriformes|united_kingdom|13_1_4_1_4_1_1_4|2023-04-28">
			<date value="2023.3205479452056" direction="forwards" units="years"/>
		</taxon>
		<taxon id="H5N1|2344b|EPI_ISL_17716780|charadriiformes|denmark|1_1_4_1_4_1_1_4|2023-05-01">
			<date value="2023.3287671232877" direction="forwards" units="years"/>
		</taxon>
		<taxon id="H5N1|2344b|EPI_ISL_17716813|charadriiformes|czechia|1_1_4_1_4_1_1_4|2023-04-24">
			<date value="2023.309589041096" direction="forwards" units="years"/>
		</taxon>
		<taxon id="H5N1|2344b|EPI_ISL_17716817|charadriiformes|czechia|1_1_4_1_4_1_1_4|2023-05-03">
			<date value="2023.3342465753424" direction="forwards" units="years"/>
		</taxon>
		<taxon id="H5N1|2344b|EPI_ISL_17716820|galliformes|czechia|1_1_4_1_4_1_1_4|2023-05-05">
			<date value="2023.3397260273973" direction="forwards" units="years"/>
		</taxon>
		<taxon id="H5N1|2344b|EPI_ISL_17716824|charadriiformes|czechia|1_1_4_1_4_1_1_4|2023-05-11">
			<date value="2023.3561643835617" direction="forwards" units="years"/>
		</taxon>
		<taxon id="H5N1|2344b|EPI_ISL_17762861|charadriiformes|croatia|1_1_4_1_4_1_1_4|2023-05-15">
			<date value="2023.3671232876711" direction="forwards" units="years"/>
		</taxon>
		<taxon id="H5N1|2344b|EPI_ISL_17787128|falconiformes|sweden|1_1_4_1_4_1_1_4|2023-05-06">
			<date value="2023.3424657534247" direction="forwards" units="years"/>
		</taxon>
		<taxon id="H5N1|2344b|EPI_ISL_17787586|charadriiformes|sweden|1_1_4_1_4_1_1_4|2023-05-29">
			<date value="2023.4054794520548" direction="forwards" units="years"/>
		</taxon>
		<taxon id="H5N1|2344b|EPI_ISL_17821059|charadriiformes|netherlands|1_1_4_1_4_1_1_4|2023-05-28">
			<date value="2023.4027397260274" direction="forwards" units="years"/>
		</taxon>
		<taxon id="H5N1|2344b|EPI_ISL_17821062|charadriiformes|netherlands|1_1_4_1_4_1_1_4|2023-02-11">
			<date value="2023.1123287671232" direction="forwards" units="years"/>
		</taxon>
		<taxon id="H5N1|2344b|EPI_ISL_17821074|charadriiformes|netherlands|1_1_4_1_4_1_1_4|2023-06-03">
			<date value="2023.4191780821918" direction="forwards" units="years"/>
		</taxon>
		<taxon id="H5N1|2344b|EPI_ISL_17514166|anseriformes|austria|1_1_2_1_1_1_1_1|2023-01-31">
			<date value="2023.0821917808219" direction="forwards" units="years"/>
		</taxon>
		<taxon id="H5N1|2344b|EPI_ISL_17514134|charadriiformes|austria|1_1_2_1_1_1_1_1|2023-03-14">
			<date value="2023.1972602739727" direction="forwards" units="years"/>
		</taxon>
		<taxon id="H5N1|2344b|EPI_ISL_17514133|charadriiformes|austria|1_1_4_1_4_1_1_4|2023-03-07">
			<date value="2023.1780821917807" direction="forwards" units="years"/>
		</taxon>
		<taxon id="H5N1|2344b|EPI_ISL_17514128|anseriformes|austria|1_1_2_1_1_1_1_1|2023-01-10">
			<date value="2023.0246575342467" direction="forwards" units="years"/>
		</taxon>
		<taxon id="H5N1|2344b|EPI_ISL_18006920|charadriiformes|germany|2_1_1_1_10_1_1_1|2022-01-10">
			<date value="2022.0246575342467" direction="forwards" units="years"/>
		</taxon>
		<taxon id="H5N1|2344b|EPI_ISL_18006941|anseriformes|germany|1_1_2_1_1_1_1_1|2022-04-08">
			<date value="2022.2657534246575" direction="forwards" units="years"/>
		</taxon>
		<taxon id="H5N1|2344b|EPI_ISL_18033167|anseriformes|poland|1_1_2_1_1_1_1_1|2023-01-16">
			<date value="2023.041095890411" direction="forwards" units="years"/>
		</taxon>
		<taxon id="H5N1|2344b|EPI_ISL_18033185|charadriiformes|poland|13_1_4_1_4_1_1_4|2023-02-07">
			<date value="2023.1013698630136" direction="forwards" units="years"/>
		</taxon>
		<taxon id="H5N1|2344b|EPI_ISL_18033200|charadriiformes|poland|13_1_4_1_4_1_1_4|2023-03-13">
			<date value="2023.194520547945" direction="forwards" units="years"/>
		</taxon>
		<taxon id="H5N1|2344b|EPI_ISL_18033235|charadriiformes|poland|1_1_4_1_4_1_1_4|2023-05-30">
			<date value="2023.4082191780822" direction="forwards" units="years"/>
		</taxon>
		<taxon id="H5N1|2344b|EPI_ISL_18040892|anseriformes|poland|1_1_2_1_1_1_1_1|2023-01-19">
			<date value="2023.0493150684931" direction="forwards" units="years"/>
		</taxon>
		<taxon id="H5N1|2344b|EPI_ISL_18064620|charadriiformes|netherlands|13_1_4_1_4_1_1_4|2023-05-12">
			<date value="2023.358904109589" direction="forwards" units="years"/>
		</taxon>
		<taxon id="H5N1|2344b|EPI_ISL_18065348|charadriiformes|united_kingdom|1_1_4_1_4_1_1_4|2023-06-27">
			<date value="2023.4849315068493" direction="forwards" units="years"/>
		</taxon>
		<taxon id="H5N1|2344b|EPI_ISL_18071580|anseriformes|russia|2_1_1_1_1_1_1_1|2022-10-09">
			<date value="2022.7698630136986" direction="forwards" units="years"/>
		</taxon>
		<taxon id="H5N1|2344b|EPI_ISL_18074199|passeriformes|russia|2_1_1_1_1_1_1_1|2022-04-15">
			<date value="2022.2849315068493" direction="forwards" units="years"/>
		</taxon>
		<taxon id="H5N1|2344b|EPI_ISL_18161874|primates|united_kingdom|13_1_4_1_4_1_1_4|2023-07-07">
			<date value="2023.5123287671233" direction="forwards" units="years"/>
		</taxon>
		<taxon id="H5N1|2344b|EPI_ISL_18219237|anseriformes|france|2_1_1_1_1_1_1_1|2022-02-03">
			<date value="2022.0904109589042" direction="forwards" units="years"/>
		</taxon>
		<taxon id="H5N1|2344b|EPI_ISL_18245742|anseriformes|poland|2_1_1_1_9_1_1_1|2022-01-14">
			<date value="2022.035616438356" direction="forwards" units="years"/>
		</taxon>
		<taxon id="H5N1|2344b|EPI_ISL_18245789|anseriformes|poland|2_6_1_1_9_1_1_1|2022-01-24">
			<date value="2022.0630136986301" direction="forwards" units="years"/>
		</taxon>
		<taxon id="H5N1|2344b|EPI_ISL_18245790|anseriformes|poland|2_1_1_1_9_1_1_1|2022-02-03">
			<date value="2022.0904109589042" direction="forwards" units="years"/>
		</taxon>
		<taxon id="H5N1|2344b|EPI_ISL_18245812|NA|poland|1_1_1_1_1_1_1_1|2021-12-20">
			<date value="2021.9671232876713" direction="forwards" units="years"/>
		</taxon>
		<taxon id="H5N1|2344b|EPI_ISL_18245813|accipitriformes|poland|1_1_1_1_1_1_1_1|2021-12-22">
			<date value="2021.972602739726" direction="forwards" units="years"/>
		</taxon>
		<taxon id="H5N1|2344b|EPI_ISL_18245816|anseriformes|poland|2_6_1_1_6_1_1_1|2022-04-07">
			<date value="2022.2630136986302" direction="forwards" units="years"/>
		</taxon>
		<taxon id="H5N1|2344b|EPI_ISL_18255288|falconiformes|sweden|1_1_4_1_4_1_1_4|2023-07-20">
			<date value="2023.5479452054794" direction="forwards" units="years"/>
		</taxon>
		<taxon id="H5N1|2344b|EPI_ISL_18271509|charadriiformes|denmark|1_1_4_1_4_1_1_4|2023-06-22">
			<date value="2023.4712328767123" direction="forwards" units="years"/>
		</taxon>
		<taxon id="H5N1|2344b|EPI_ISL_18271510|charadriiformes|denmark|13_1_4_1_4_1_1_4|2023-07-30">
			<date value="2023.5753424657535" direction="forwards" units="years"/>
		</taxon>
		<taxon id="H5N1|2344b|EPI_ISL_18432789|falconiformes|germany|13_1_4_1_18_1_1_4|2023-09-07">
			<date value="2023.682191780822" direction="forwards" units="years"/>
		</taxon>
		<taxon id="H5N1|2344b|EPI_ISL_18458060|anseriformes|poland|2_1_1_1_1_1_1_1|2021-11-12">
			<date value="2021.86301369863" direction="forwards" units="years"/>
		</taxon>
		<taxon id="H5N1|2344b|EPI_ISL_18458072|galliformes|austria|2_1_1_1_1_1_1_1|2021-11-29">
			<date value="2021.9095890410958" direction="forwards" units="years"/>
		</taxon>
		<taxon id="H5N1|2344b|EPI_ISL_18458074|anseriformes|austria|1_1_2_1_1_1_1_1|2021-12-09">
			<date value="2021.9369863013699" direction="forwards" units="years"/>
		</taxon>
		<taxon id="H5N1|2344b|EPI_ISL_18458690|strigiformes|germany|14_1_3_1_1_1_1_1|2023-03-06">
			<date value="2023.1753424657534" direction="forwards" units="years"/>
		</taxon>
		<taxon id="H5N1|2344b|EPI_ISL_18458691|anseriformes|germany|1_1_2_1_1_1_1_1|2023-01-19">
			<date value="2023.0493150684931" direction="forwards" units="years"/>
		</taxon>
		<taxon id="H5N1|2344b|EPI_ISL_18490247|charadriiformes|netherlands|1_1_4_1_4_1_1_4|2023-10-17">
			<date value="2023.7917808219179" direction="forwards" units="years"/>
		</taxon>
		<taxon id="H5N1|2344b|EPI_ISL_18506030|anseriformes|netherlands|1_6_2_1_1_1_1_1|2023-11-05">
			<date value="2023.8438356164384" direction="forwards" units="years"/>
		</taxon>
		<taxon id="H5N1|2344b|EPI_ISL_18506031|accipitriformes|netherlands|18_6_2_1_14_1_1_1|2023-11-05">
			<date value="2023.8438356164384" direction="forwards" units="years"/>
		</taxon>
		<taxon id="H5N1|2344b|EPI_ISL_18506032|anseriformes|netherlands|1_6_2_1_1_1_1_1|2023-11-07">
			<date value="2023.849315068493" direction="forwards" units="years"/>
		</taxon>
		<taxon id="H5N1|2344b|EPI_ISL_18509068|charadriiformes|latvia|1_1_4_1_4_1_1_4|2023-05-29">
			<date value="2023.4054794520548" direction="forwards" units="years"/>
		</taxon>
		<taxon id="H5N1|2344b|EPI_ISL_18509073|anseriformes|latvia|2_1_1_1_1_1_1_1|2022-01-14">
			<date value="2022.035616438356" direction="forwards" units="years"/>
		</taxon>
		<taxon id="H5N1|2344b|EPI_ISL_18514139|falconiformes|sweden|1_1_4_1_4_1_1_4|2023-07-02">
			<date value="2023.4986301369863" direction="forwards" units="years"/>
		</taxon>
		<taxon id="H5N1|2344b|EPI_ISL_18514426|falconiformes|sweden|1_1_2_1_1_1_1_1|2023-06-23">
			<date value="2023.4739726027397" direction="forwards" units="years"/>
		</taxon>
		<taxon id="H5N1|2344b|EPI_ISL_18540525|anseriformes|austria|10_6_2_1_1_1_1_1|2023-10-23">
			<date value="2023.8082191780823" direction="forwards" units="years"/>
		</taxon>
		<taxon id="H5N1|2344b|EPI_ISL_18612231|ciconiiformes|slovenia|10_6_2_1_1_1_1_1|2023-09-14">
			<date value="2023.7013698630137" direction="forwards" units="years"/>
		</taxon>
		<taxon id="H5N1|2344b|EPI_ISL_18612269|anseriformes|italy|10_6_2_1_1_1_1_1|2023-11-09">
			<date value="2023.854794520548" direction="forwards" units="years"/>
		</taxon>
		<taxon id="H5N1|2344b|EPI_ISL_17985402|charadriiformes|netherlands|13_1_4_1_4_1_1_4|2023-06-16">
			<date value="2023.454794520548" direction="forwards" units="years"/>
		</taxon>
		<taxon id="H5N1|2344b|EPI_ISL_17985409|charadriiformes|netherlands|1_1_4_1_4_1_1_4|2023-06-20">
			<date value="2023.4657534246576" direction="forwards" units="years"/>
		</taxon>
		<taxon id="H5N1|2344b|EPI_ISL_18001810|galliformes|iceland|2_1_1_1_1_1_1_1|2022-04-15">
			<date value="2022.2849315068493" direction="forwards" units="years"/>
		</taxon>
		<taxon id="H5N1|2344b|EPI_ISL_18001816|anseriformes|iceland|1_1_2_1_1_1_1_1|2022-04-19">
			<date value="2022.295890410959" direction="forwards" units="years"/>
		</taxon>
		<taxon id="H5N1|2344b|EPI_ISL_18058688|charadriiformes|austria|1_1_4_1_4_1_1_4|2023-03-28">
			<date value="2023.2356164383561" direction="forwards" units="years"/>
		</taxon>
		<taxon id="H5N1|2344b|EPI_ISL_18058694|charadriiformes|austria|1_1_4_1_4_1_1_4|2023-05-23">
			<date value="2023.3890410958904" direction="forwards" units="years"/>
		</taxon>
		<taxon id="H5N1|2344b|EPI_ISL_18059056|charadriiformes|netherlands|13_1_4_1_4_1_1_4|2023-07-11">
			<date value="2023.5232876712328" direction="forwards" units="years"/>
		</taxon>
		<taxon id="H5N1|2344b|EPI_ISL_18075143|charadriiformes|netherlands|1_1_4_1_4_1_1_4|2023-03-07">
			<date value="2023.1780821917807" direction="forwards" units="years"/>
		</taxon>
		<taxon id="H5N1|2344b|EPI_ISL_18075146|falconiformes|netherlands|1_1_4_1_4_1_1_4|2023-01-31">
			<date value="2023.0821917808219" direction="forwards" units="years"/>
		</taxon>
		<taxon id="H5N1|2344b|EPI_ISL_18075147|falconiformes|netherlands|1_1_4_1_4_1_1_4|2023-03-10">
			<date value="2023.186301369863" direction="forwards" units="years"/>
		</taxon>
		<taxon id="H5N1|2344b|EPI_ISL_18255396|charadriiformes|sweden|1_1_4_1_4_1_1_4|2023-07-20">
			<date value="2023.5479452054794" direction="forwards" units="years"/>
		</taxon>
		<taxon id="H5N1|2344b|EPI_ISL_18361501|pelecaniformes|croatia|2_1_1_1_1_1_1_1|2021-11-16">
			<date value="2021.8739726027397" direction="forwards" units="years"/>
		</taxon>
		<taxon id="H5N1|2344b|EPI_ISL_18378729|galliformes|united_kingdom|13_1_4_1_4_1_1_4|2023-08-20">
			<date value="2023.6328767123289" direction="forwards" units="years"/>
		</taxon>
		<taxon id="H5N1|2344b|EPI_ISL_18435608|falconiformes|germany|1_1_4_1_4_1_1_4|2023-08-02">
			<date value="2023.5835616438355" direction="forwards" units="years"/>
		</taxon>
		<taxon id="H5N1|2344b|EPI_ISL_18435609|charadriiformes|germany|13_1_4_1_4_1_1_4|2023-07-26">
			<date value="2023.5643835616438" direction="forwards" units="years"/>
		</taxon>
		<taxon id="H5N1|2344b|EPI_ISL_18010407|charadriiformes|united_kingdom|13_1_4_1_4_1_1_4|2023-06-05">
			<date value="2023.4246575342465" direction="forwards" units="years"/>
		</taxon>
		<taxon id="H5N1|2344b|EPI_ISL_18010913|charadriiformes|netherlands|1_1_4_1_4_1_1_4|2023-06-23">
			<date value="2023.4739726027397" direction="forwards" units="years"/>
		</taxon>
		<taxon id="H5N1|2344b|EPI_ISL_18011065|carnivora|finland|1_1_4_1_4_1_1_4|2023-07-14">
			<date value="2023.531506849315" direction="forwards" units="years"/>
		</taxon>
		<taxon id="H5N1|2344b|EPI_ISL_18075722|charadriiformes|spain|1_1_4_1_4_1_1_4|2023-06-20">
			<date value="2023.4657534246576" direction="forwards" units="years"/>
		</taxon>
		<taxon id="H5N1|2344b|EPI_ISL_18075816|accipitriformes|spain|1_1_2_1_1_1_1_1|2022-06-09">
			<date value="2022.4356164383562" direction="forwards" units="years"/>
		</taxon>
		<taxon id="H5N1|2344b|EPI_ISL_18076012|galliformes|italy|1_1_6_1_9_1_1_1|2023-07-10">
			<date value="2023.5205479452054" direction="forwards" units="years"/>
		</taxon>
		<taxon id="H5N1|2344b|EPI_ISL_18076013|galliformes|italy|1_1_6_1_9_1_1_1|2023-07-10">
			<date value="2023.5205479452054" direction="forwards" units="years"/>
		</taxon>
		<taxon id="H5N1|2344b|EPI_ISL_18321748|charadriiformes|finland|1_1_4_1_4_1_1_4|2023-07-12">
			<date value="2023.5260273972603" direction="forwards" units="years"/>
		</taxon>
		<taxon id="H5N1|2344b|EPI_ISL_18420062|anseriformes|croatia|1_1_2_1_1_1_1_1|2022-02-09">
			<date value="2022.1068493150685" direction="forwards" units="years"/>
		</taxon>
		<taxon id="H5N1|2344b|EPI_ISL_18591991|gruiformes|austria|10_6_2_1_1_1_1_1|2023-11-14">
			<date value="2023.868493150685" direction="forwards" units="years"/>
		</taxon>
		<taxon id="H5N1|2344b|EPI_ISL_18591992|gruiformes|austria|10_6_2_1_1_1_1_1|2023-11-20">
			<date value="2023.8849315068494" direction="forwards" units="years"/>
		</taxon>
		<taxon id="H5N1|2344b|EPI_ISL_18591993|gruiformes|austria|10_6_2_1_1_1_1_1|2023-11-21">
			<date value="2023.8876712328768" direction="forwards" units="years"/>
		</taxon>
		<taxon id="H5N1|2344b|EPI_ISL_17971992|carnivora|poland|1_1_2_1_1_1_1_1|2023-06-26">
			<date value="2023.482191780822" direction="forwards" units="years"/>
		</taxon>
		<taxon id="H5N1|2344b|EPI_ISL_18011232|accipitriformes|finland|1_1_2_1_1_1_1_1|2023-06-28">
			<date value="2023.4876712328767" direction="forwards" units="years"/>
		</taxon>
		<taxon id="H5N1|2344b|EPI_ISL_18013308|charadriiformes|germany|1_1_4_1_4_1_1_4|2023-06-02">
			<date value="2023.4164383561645" direction="forwards" units="years"/>
		</taxon>
		<taxon id="H5N1|2344b|EPI_ISL_18013310|charadriiformes|germany|1_1_4_1_4_1_1_4|2023-06-05">
			<date value="2023.4246575342465" direction="forwards" units="years"/>
		</taxon>
		<taxon id="H5N1|2344b|EPI_ISL_18112332|galliformes|jersey|1_1_4_1_4_1_1_4|2023-07-17">
			<date value="2023.5397260273974" direction="forwards" units="years"/>
		</taxon>
		<taxon id="H5N1|2344b|EPI_ISL_18118722|charadriiformes|netherlands|1_1_4_1_4_1_1_4|2023-07-21">
			<date value="2023.5506849315068" direction="forwards" units="years"/>
		</taxon>
		<taxon id="H5N1|2344b|EPI_ISL_18161267|charadriiformes|russia|1_1_4_1_4_1_1_4|2023-08-14">
			<date value="2023.6164383561643" direction="forwards" units="years"/>
		</taxon>
		<taxon id="H5N1|2344b|EPI_ISL_18209363|galliformes|united_kingdom|13_1_4_1_4_1_1_4|2023-08-08">
			<date value="2023.6" direction="forwards" units="years"/>
		</taxon>
		<taxon id="H5N1|2344b|EPI_ISL_18257880|charadriiformes|sweden|1_1_4_1_4_1_1_4|2023-06-22">
			<date value="2023.4712328767123" direction="forwards" units="years"/>
		</taxon>
		<taxon id="H5N1|2344b|EPI_ISL_18290481|carnivora|finland|1_1_4_1_4_1_1_4|2023-08-07">
			<date value="2023.5972602739726" direction="forwards" units="years"/>
		</taxon>
		<taxon id="H5N1|2344b|EPI_ISL_18439561|galliformes|united_kingdom|13_1_4_1_4_1_1_4|2023-09-24">
			<date value="2023.7287671232878" direction="forwards" units="years"/>
		</taxon>
		<taxon id="H5N1|2344b|EPI_ISL_18445703|charadriiformes|france|2_1_1_1_10_1_1_1|2022-01-20">
			<date value="2022.0520547945205" direction="forwards" units="years"/>
		</taxon>
		<taxon id="H5N1|2344b|EPI_ISL_18445705|anseriformes|france|1_1_1_1_1_1_1_1|2022-01-24">
			<date value="2022.0630136986301" direction="forwards" units="years"/>
		</taxon>
		<taxon id="H5N1|2344b|EPI_ISL_18445714|charadriiformes|france|1_1_4_1_4_1_1_4|2022-05-21">
			<date value="2022.3835616438357" direction="forwards" units="years"/>
		</taxon>
		<taxon id="H5N1|2344b|EPI_ISL_18445751|suliformes|france|2_1_1_1_1_1_1_1|2022-07-25">
			<date value="2022.5616438356165" direction="forwards" units="years"/>
		</taxon>
		<taxon id="H5N1|2344b|EPI_ISL_18455202|suliformes|norway|2_1_1_1_1_1_1_1|2022-06-16">
			<date value="2022.454794520548" direction="forwards" units="years"/>
		</taxon>
		<taxon id="H5N1|2344b|EPI_ISL_18455203|carnivora|norway|2_1_1_1_1_1_1_1|2022-07-26">
			<date value="2022.5643835616438" direction="forwards" units="years"/>
		</taxon>
		<taxon id="H5N1|2344b|EPI_ISL_18455216|galliformes|norway|2_1_1_1_1_1_1_1|2021-11-10">
			<date value="2021.8575342465754" direction="forwards" units="years"/>
		</taxon>
		<taxon id="H5N1|2344b|EPI_ISL_18530057|galliformes|denmark|1_1_2_1_1_1_1_1|2023-09-26">
			<date value="2023.7342465753425" direction="forwards" units="years"/>
		</taxon>
		<taxon id="H5N1|2344b|EPI_ISL_18530147|galliformes|denmark|1_6_2_1_1_1_1_1|2023-11-11">
			<date value="2023.8602739726027" direction="forwards" units="years"/>
		</taxon>
		<taxon id="H5N1|2344b|EPI_ISL_18538399|galliformes|united_kingdom|18_1_2_1_1_1_1_1|2023-09-06">
			<date value="2023.6794520547944" direction="forwards" units="years"/>
		</taxon>
		<taxon id="H5N1|2344b|EPI_ISL_18538400|galliformes|united_kingdom|18_1_2_1_1_1_1_1|2023-09-06">
			<date value="2023.6794520547944" direction="forwards" units="years"/>
		</taxon>
		<taxon id="H5N1|2344b|EPI_ISL_18538401|galliformes|united_kingdom|18_9_2_1_1_1_1_1|2023-09-08">
			<date value="2023.6849315068494" direction="forwards" units="years"/>
		</taxon>
		<taxon id="H5N1|2344b|EPI_ISL_18538402|galliformes|united_kingdom|18_9_2_1_1_1_1_1|2023-09-08">
			<date value="2023.6849315068494" direction="forwards" units="years"/>
		</taxon>
		<taxon id="H5N1|2344b|EPI_ISL_18538403|galliformes|united_kingdom|18_1_2_1_1_1_1_1|2023-09-26">
			<date value="2023.7342465753425" direction="forwards" units="years"/>
		</taxon>
		<taxon id="H5N1|2344b|EPI_ISL_18538404|galliformes|united_kingdom|18_1_2_1_1_1_1_1|2023-09-26">
			<date value="2023.7342465753425" direction="forwards" units="years"/>
		</taxon>
		<taxon id="H5N1|2344b|EPI_ISL_18538405|galliformes|united_kingdom|18_1_2_1_1_1_1_1|2023-09-26">
			<date value="2023.7342465753425" direction="forwards" units="years"/>
		</taxon>
		<taxon id="H5N1|2344b|EPI_ISL_18538406|galliformes|united_kingdom|18_9_2_1_1_1_1_1|2023-10-06">
			<date value="2023.7616438356165" direction="forwards" units="years"/>
		</taxon>
		<taxon id="H5N1|2344b|EPI_ISL_18538407|galliformes|united_kingdom|18_9_2_1_1_1_1_1|2023-10-22">
			<date value="2023.805479452055" direction="forwards" units="years"/>
		</taxon>
		<taxon id="H5N1|2344b|EPI_ISL_18538408|galliformes|united_kingdom|18_9_2_1_1_1_1_1|2023-10-22">
			<date value="2023.805479452055" direction="forwards" units="years"/>
		</taxon>
		<taxon id="H5N1|2344b|EPI_ISL_18538410|galliformes|united_kingdom|18_1_2_1_1_1_1_1|2023-09-06">
			<date value="2023.6794520547944" direction="forwards" units="years"/>
		</taxon>
		<taxon id="H5N1|2344b|EPI_ISL_18538412|galliformes|united_kingdom|18_1_2_1_1_1_1_1|2023-09-06">
			<date value="2023.6794520547944" direction="forwards" units="years"/>
		</taxon>
		<taxon id="H5N1|2344b|EPI_ISL_18578957|galliformes|denmark|1_6_2_1_1_1_1_1|2023-11-20">
			<date value="2023.8849315068494" direction="forwards" units="years"/>
		</taxon>
		<taxon id="H5N1|2344b|EPI_ISL_18586149|gruiformes|france|10_6_2_1_1_1_1_1|2023-11-19">
			<date value="2023.8821917808218" direction="forwards" units="years"/>
		</taxon>
		<taxon id="H5N1|2344b|EPI_ISL_18592418|suliformes|united_kingdom|1_6_2_1_1_1_1_1|2023-11-01">
			<date value="2023.8328767123287" direction="forwards" units="years"/>
		</taxon>
		<taxon id="H5N1|2344b|EPI_ISL_18594303|carnivora|denmark|1_1_2_1_1_1_1_1|2023-04-29">
			<date value="2023.323287671233" direction="forwards" units="years"/>
		</taxon>
		<taxon id="H5N1|2344b|EPI_ISL_18612177|charadriiformes|slovenia|1_1_4_1_4_1_1_4|2023-05-16">
			<date value="2023.3698630136987" direction="forwards" units="years"/>
		</taxon>
		<taxon id="H5N1|2344b|EPI_ISL_18612182|anseriformes|romania|10_6_2_1_1_1_1_1|2023-10-30">
			<date value="2023.827397260274" direction="forwards" units="years"/>
		</taxon>
		<taxon id="H5N1|2344b|EPI_ISL_18652553|anseriformes|NA|1_1_2_1_1_1_1_1|2022-10-12">
			<date value="2022.7780821917809" direction="forwards" units="years"/>
		</taxon>
		<taxon id="H5N1|2344b|EPI_ISL_18652555|phoenicopteriformes|italy|2_1_2_1_1_1_1_1|2022-11-07">
			<date value="2022.849315068493" direction="forwards" units="years"/>
		</taxon>
		<taxon id="H5N1|2344b|EPI_ISL_18660627|charadriiformes|netherlands|1_1_4_1_4_1_1_4|2023-11-12">
			<date value="2023.86301369863" direction="forwards" units="years"/>
		</taxon>
		<taxon id="H5N1|2344b|EPI_ISL_18660629|charadriiformes|netherlands|1_1_2_1_1_1_1_1|2023-11-12">
			<date value="2023.86301369863" direction="forwards" units="years"/>
		</taxon>
		<taxon id="H5N1|2344b|EPI_ISL_18660931|anseriformes|sweden|10_1_2_1_1_1_1_1|2023-11-24">
			<date value="2023.8958904109588" direction="forwards" units="years"/>
		</taxon>
		<taxon id="H5N1|2344b|EPI_ISL_18668515|charadriiformes|belgium|1_6_2_1_1_1_1_1|2023-12-08">
			<date value="2023.9342465753425" direction="forwards" units="years"/>
		</taxon>
		<taxon id="H5N1|2344b|EPI_ISL_18668521|anseriformes|united_kingdom|1_6_2_1_1_1_1_1|2023-11-28">
			<date value="2023.9068493150685" direction="forwards" units="years"/>
		</taxon>
		<taxon id="H5N1|2344b|EPI_ISL_18683420|galliformes|ukraine|10_6_2_1_1_1_1_1|2023-03-21">
			<date value="2023.2164383561644" direction="forwards" units="years"/>
		</taxon>
		<taxon id="H5N1|2344b|EPI_ISL_18325132|falconiformes|united_kingdom|13_1_4_1_4_1_1_4|2023-07-25">
			<date value="2023.5616438356165" direction="forwards" units="years"/>
		</taxon>
		<taxon id="H5N1|2344b|EPI_ISL_18325127|charadriiformes|united_kingdom|13_1_4_1_4_1_1_4|2023-07-14">
			<date value="2023.531506849315" direction="forwards" units="years"/>
		</taxon>
		<taxon id="H5N1|2344b|EPI_ISL_18956184|falconiformes|cyprus|10_1_2_1_1_1_1_1|2024-01-05">
			<date value="2024.0109289617487" direction="forwards" units="years"/>
		</taxon>
		<taxon id="H5N1|2344b|EPI_ISL_18946775|anseriformes|czechia|1_1_2_1_1_1_1_7|2024-02-07">
			<date value="2024.1010928961748" direction="forwards" units="years"/>
		</taxon>
		<taxon id="H5N1|2344b|EPI_ISL_18929001|anseriformes|czechia|1_1_2_1_1_1_1_7|2024-01-25">
			<date value="2024.0655737704917" direction="forwards" units="years"/>
		</taxon>
		<taxon id="H5N1|2344b|EPI_ISL_18866886|charadriiformes|sweden|2_1_2_1_1_1_1_1|2024-01-07">
			<date value="2024.016393442623" direction="forwards" units="years"/>
		</taxon>
		<taxon id="H5N1|2344b|EPI_ISL_18983379|charadriiformes|spain|1_1_4_1_4_1_1_4|2023-03-07">
			<date value="2023.1780821917807" direction="forwards" units="years"/>
		</taxon>
		<taxon id="H5N1|2344b|EPI_ISL_19001972|galliformes|sweden|2_1_2_1_1_1_1_1|2024-03-15">
			<date value="2024.2021857923498" direction="forwards" units="years"/>
		</taxon>
		<taxon id="H5N1|2344b|EPI_ISL_19044794|anseriformes|czechia|1_1_2_1_1_1_1_7|2024-03-07">
			<date value="2024.1803278688524" direction="forwards" units="years"/>
		</taxon>
		<taxon id="H5N1|2344b|EPI_ISL_19033562|anseriformes|poland|1_1_2_1_1_1_1_7|2024-02-19">
			<date value="2024.1338797814208" direction="forwards" units="years"/>
		</taxon>
		<taxon id="H5N1|2344b|EPI_ISL_18956167|anseriformes|croatia|1_1_2_1_1_1_1_7|2024-01-04">
			<date value="2024.0081967213114" direction="forwards" units="years"/>
		</taxon>
		<taxon id="H5N1|2344b|EPI_ISL_18956166|anseriformes|croatia|10_6_2_1_1_1_1_1|2023-12-19">
			<date value="2023.964383561644" direction="forwards" units="years"/>
		</taxon>
		<taxon id="H5N1|2344b|EPI_ISL_18913197|anseriformes|moldova|1_1_2_1_1_1_1_7|2023-12-20">
			<date value="2023.9671232876713" direction="forwards" units="years"/>
		</taxon>
		<taxon id="H5N1|2344b|EPI_ISL_18913195|anseriformes|moldova|10_6_2_1_1_1_1_1|2023-12-21">
			<date value="2023.9698630136986" direction="forwards" units="years"/>
		</taxon>
		<taxon id="H5N1|2344b|EPI_ISL_18956179|anseriformes|romania|1_1_2_1_1_1_1_7|2024-01-03">
			<date value="2024.0054644808743" direction="forwards" units="years"/>
		</taxon>
		<taxon id="H5N1|2344b|EPI_ISL_18956172|anseriformes|romania|1_6_2_1_1_1_1_1|2023-12-21">
			<date value="2023.9698630136986" direction="forwards" units="years"/>
		</taxon>
		<taxon id="H5N1|2344b|EPI_ISL_19000795|anseriformes|sweden|10_1_2_1_1_1_1_1|2024-02-16">
			<date value="2024.1256830601094" direction="forwards" units="years"/>
		</taxon>
		<taxon id="H5N1|2344b|EPI_ISL_18946720|anseriformes|czechia|1_1_2_1_1_1_1_7|2023-02-09">
			<date value="2023.1068493150685" direction="forwards" units="years"/>
		</taxon>
		<taxon id="H5N1|2344b|EPI_ISL_18946719|anseriformes|czechia|1_1_2_1_1_1_1_7|2023-02-09">
			<date value="2023.1068493150685" direction="forwards" units="years"/>
		</taxon>
		<taxon id="H5N1|2344b|EPI_ISL_18946718|anseriformes|czechia|1_1_2_1_1_1_1_7|2023-02-09">
			<date value="2023.1068493150685" direction="forwards" units="years"/>
		</taxon>
		<taxon id="H5N1|2344b|EPI_ISL_18918508|anseriformes|sweden|10_1_2_1_1_1_1_1|2024-01-30">
			<date value="2024.0792349726776" direction="forwards" units="years"/>
		</taxon>
		<taxon id="H5N1|2344b|EPI_ISL_18916730|anseriformes|austria|1_1_2_1_1_1_1_1|2023-12-15">
			<date value="2023.9534246575342" direction="forwards" units="years"/>
		</taxon>
		<taxon id="H5N1|2344b|EPI_ISL_18815277|anseriformes|sweden|1_1_2_1_1_1_1_1|2023-12-21">
			<date value="2023.9698630136986" direction="forwards" units="years"/>
		</taxon>
		<taxon id="H5N1|2344b|EPI_ISL_19033336|galliformes|poland|1_1_2_1_1_1_1_1|2024-02-27">
			<date value="2024.155737704918" direction="forwards" units="years"/>
		</taxon>
		<taxon id="H5N1|2344b|EPI_ISL_18992914|galliformes|denmark|1_6_2_1_1_1_1_1|2023-11-04">
			<date value="2023.841095890411" direction="forwards" units="years"/>
		</taxon>
		<taxon id="H5N1|2344b|EPI_ISL_19000790|accipitriformes|sweden|1_6_2_1_1_1_1_1|2024-02-09">
			<date value="2024.1065573770493" direction="forwards" units="years"/>
		</taxon>
		<taxon id="H5N1|2344b|EPI_ISL_18916729|gruiformes|austria|10_6_2_1_1_1_1_1|2024-01-12">
			<date value="2024.0300546448088" direction="forwards" units="years"/>
		</taxon>
		<taxon id="H5N1|2344b|EPI_ISL_18824088|anseriformes|united_kingdom|1_6_2_1_1_1_1_1|2023-12-28">
			<date value="2023.9890410958903" direction="forwards" units="years"/>
		</taxon>
		<taxon id="H5N1|2344b|EPI_ISL_18824085|anseriformes|united_kingdom|10_1_2_1_1_1_1_1|2023-12-28">
			<date value="2023.9890410958903" direction="forwards" units="years"/>
		</taxon>
		<taxon id="H5N1|2344b|EPI_ISL_18742319|charadriiformes|united_kingdom|13_1_4_1_4_1_1_4|2023-11-26">
			<date value="2023.9013698630138" direction="forwards" units="years"/>
		</taxon>
		<taxon id="H5N1|2344b|EPI_ISL_18937337|carnivora|germany|10_1_2_1_1_1_1_1|2024-01-01">
			<date value="2024.0" direction="forwards" units="years"/>
		</taxon>
		<taxon id="H5N1|2344b|EPI_ISL_19047951|charadriiformes|netherlands|10_6_2_1_11_1_1_1|2024-03-11">
			<date value="2024.191256830601" direction="forwards" units="years"/>
		</taxon>
		<taxon id="H5N1|2344b|EPI_ISL_19033340|accipitriformes|poland|10_1_2_1_1_1_1_1|2024-03-04">
			<date value="2024.172131147541" direction="forwards" units="years"/>
		</taxon>
		<taxon id="H5N1|2344b|EPI_ISL_19030163|accipitriformes|germany|1_1_2_1_1_1_1_7|2024-03-04">
			<date value="2024.172131147541" direction="forwards" units="years"/>
		</taxon>
		<taxon id="H5N1|2344b|EPI_ISL_19014084|charadriiformes|germany|10_6_2_1_11_1_1_1|2024-02-09">
			<date value="2024.1065573770493" direction="forwards" units="years"/>
		</taxon>
		<taxon id="H5N1|2344b|EPI_ISL_18963393|galliformes|norway|1_1_4_1_4_1_1_4|2023-10-09">
			<date value="2023.7698630136986" direction="forwards" units="years"/>
		</taxon>
		<taxon id="H5N1|2344b|EPI_ISL_18937341|passeriformes|germany|1_6_2_1_1_1_1_10|2024-01-11">
			<date value="2024.0273224043715" direction="forwards" units="years"/>
		</taxon>
		<taxon id="H5N1|2344b|EPI_ISL_18882069|charadriiformes|netherlands|1_1_4_1_4_1_1_4|2023-07-04">
			<date value="2023.504109589041" direction="forwards" units="years"/>
		</taxon>
		<taxon id="H5N1|2344b|EPI_ISL_18746298|anseriformes|netherlands|1_1_2_1_1_1_1_1|2023-12-21">
			<date value="2023.9698630136986" direction="forwards" units="years"/>
		</taxon>
		<taxon id="H5N1|2344b|EPI_ISL_18745080|galliformes|germany|1_6_2_1_1_1_1_1|2023-11-29">
			<date value="2023.9095890410958" direction="forwards" units="years"/>
		</taxon>
		<taxon id="H5N1|2344b|EPI_ISL_18745078|galliformes|germany|10_1_2_1_1_1_1_1|2023-11-28">
			<date value="2023.9068493150685" direction="forwards" units="years"/>
		</taxon>
		<taxon id="H5N1|2344b|EPI_ISL_18745077|galliformes|germany|1_6_2_1_1_1_1_1|2023-11-24">
			<date value="2023.8958904109588" direction="forwards" units="years"/>
		</taxon>
		<taxon id="H5N1|2344b|EPI_ISL_18729430|accipitriformes|netherlands|1_6_2_1_1_1_1_1|2023-03-14">
			<date value="2023.1972602739727" direction="forwards" units="years"/>
		</taxon>
		<taxon id="H5N1|2344b|EPI_ISL_18729429|anseriformes|netherlands|1_6_2_1_1_1_1_1|2023-11-27">
			<date value="2023.9041095890411" direction="forwards" units="years"/>
		</taxon>
		<taxon id="H5N1|2344b|EPI_ISL_18729427|anseriformes|netherlands|1_6_2_1_1_1_1_1|2023-11-27">
			<date value="2023.9041095890411" direction="forwards" units="years"/>
		</taxon>
		<taxon id="H5N1|2344b|EPI_ISL_19044795|galliformes|czechia|1_1_2_1_1_1_1_7|2024-03-14">
			<date value="2024.1994535519125" direction="forwards" units="years"/>
		</taxon>
		<taxon id="H5N1|2344b|EPI_ISL_19044790|galliformes|czechia|10_6_2_1_1_1_1_1|2024-02-26">
			<date value="2024.1530054644809" direction="forwards" units="years"/>
		</taxon>
		<taxon id="H5N1|2344b|EPI_ISL_19044789|galliformes|czechia|10_6_2_1_1_1_1_1|2024-02-26">
			<date value="2024.1530054644809" direction="forwards" units="years"/>
		</taxon>
		<taxon id="H5N1|2344b|EPI_ISL_19044788|galliformes|czechia|10_6_2_1_1_1_1_1|2024-02-26">
			<date value="2024.1530054644809" direction="forwards" units="years"/>
		</taxon>
		<taxon id="H5N1|2344b|EPI_ISL_19044787|galliformes|czechia|10_6_2_1_1_1_1_1|2024-02-26">
			<date value="2024.1530054644809" direction="forwards" units="years"/>
		</taxon>
		<taxon id="H5N1|2344b|EPI_ISL_19044784|galliformes|czechia|10_6_2_1_1_1_1_1|2024-02-24">
			<date value="2024.1475409836066" direction="forwards" units="years"/>
		</taxon>
		<taxon id="H5N1|2344b|EPI_ISL_19033549|galliformes|poland|2_1_2_1_1_1_1_1|2024-02-12">
			<date value="2024.1147540983607" direction="forwards" units="years"/>
		</taxon>
		<taxon id="H5N1|2344b|EPI_ISL_19033337|galliformes|poland|10_1_2_1_1_1_1_1|2024-02-26">
			<date value="2024.1530054644809" direction="forwards" units="years"/>
		</taxon>
		<taxon id="H5N1|2344b|EPI_ISL_19000412|galliformes|czechia|1_1_2_1_1_1_1_7|2024-02-26">
			<date value="2024.1530054644809" direction="forwards" units="years"/>
		</taxon>
		<taxon id="H5N1|2344b|EPI_ISL_19000410|galliformes|czechia|10_6_2_1_1_1_1_1|2024-02-26">
			<date value="2024.1530054644809" direction="forwards" units="years"/>
		</taxon>
		<taxon id="H5N1|2344b|EPI_ISL_19000409|galliformes|czechia|10_6_2_1_1_1_1_1|2024-02-26">
			<date value="2024.1530054644809" direction="forwards" units="years"/>
		</taxon>
		<taxon id="H5N1|2344b|EPI_ISL_18946773|galliformes|czechia|1_1_2_1_1_1_1_7|2024-02-07">
			<date value="2024.1010928961748" direction="forwards" units="years"/>
		</taxon>
		<taxon id="H5N1|2344b|EPI_ISL_18946726|galliformes|czechia|1_1_2_1_1_1_1_7|2024-02-20">
			<date value="2024.136612021858" direction="forwards" units="years"/>
		</taxon>
		<taxon id="H5N1|2344b|EPI_ISL_18928990|galliformes|czechia|1_1_2_1_1_1_1_7|2024-02-02">
			<date value="2024.0874316939892" direction="forwards" units="years"/>
		</taxon>
		<taxon id="H5N1|2344b|EPI_ISL_18928977|galliformes|czechia|10_6_2_1_1_1_1_1|2024-02-05">
			<date value="2024.0956284153006" direction="forwards" units="years"/>
		</taxon>
		<taxon id="H5N1|2344b|EPI_ISL_18927384|galliformes|united_kingdom|1_1_1_1_1_1_1_1|2024-02-14">
			<date value="2024.120218579235" direction="forwards" units="years"/>
		</taxon>
		<taxon id="H5N1|2344b|EPI_ISL_18916771|galliformes|austria|1_1_2_1_1_1_1_7|2024-02-01">
			<date value="2024.0846994535518" direction="forwards" units="years"/>
		</taxon>
		<taxon id="H5N1|2344b|EPI_ISL_18886297|galliformes|czechia|10_6_2_1_1_1_1_1|2024-01-12">
			<date value="2024.0300546448088" direction="forwards" units="years"/>
		</taxon>
		<taxon id="H5N1|2344b|EPI_ISL_18886292|galliformes|czechia|10_6_2_1_1_1_1_1|2024-01-05">
			<date value="2024.0109289617487" direction="forwards" units="years"/>
		</taxon>
		<taxon id="H5N1|2344b|EPI_ISL_18867005|galliformes|czechia|1_1_2_1_1_1_1_7|2024-01-30">
			<date value="2024.0792349726776" direction="forwards" units="years"/>
		</taxon>
		<taxon id="H5N1|2344b|EPI_ISL_18858133|galliformes|czechia|10_6_2_1_1_1_1_1|2024-01-04">
			<date value="2024.0081967213114" direction="forwards" units="years"/>
		</taxon>
		<taxon id="H5N1|2344b|EPI_ISL_18858103|galliformes|czechia|10_6_2_1_1_1_1_1|2024-01-05">
			<date value="2024.0109289617487" direction="forwards" units="years"/>
		</taxon>
		<taxon id="H5N1|2344b|EPI_ISL_18788868|galliformes|czechia|10_6_2_1_1_1_1_1|2024-01-04">
			<date value="2024.0081967213114" direction="forwards" units="years"/>
		</taxon>
		<taxon id="H5N1|2344b|EPI_ISL_18788860|galliformes|czechia|10_6_2_1_1_1_1_1|2023-12-31">
			<date value="2023.9972602739726" direction="forwards" units="years"/>
		</taxon>
		<taxon id="H5N1|2344b|EPI_ISL_18782578|galliformes|austria|14_6_1_1_1_1_1_5|2023-12-29">
			<date value="2023.9917808219177" direction="forwards" units="years"/>
		</taxon>
		<taxon id="H5N1|2344b|EPI_ISL_18953070|galliformes|denmark|1_6_2_1_1_1_1_10|2024-02-15">
			<date value="2024.122950819672" direction="forwards" units="years"/>
		</taxon>
		<taxon id="H5N1|2344b|EPI_ISL_18933100|galliformes|norway|1_1_2_1_1_1_1_1|2024-02-18">
			<date value="2024.1311475409836" direction="forwards" units="years"/>
		</taxon>
		<taxon id="H5N1|2344b|EPI_ISL_18946741|anseriformes|czechia|1_1_2_1_1_1_1_1|2024-02-09">
			<date value="2024.1065573770493" direction="forwards" units="years"/>
		</taxon>
		<taxon id="H5N1|2344b|EPI_ISL_18788587|accipitriformes|denmark|2_1_1_1_1_1_1_1|2022-01-16">
			<date value="2022.041095890411" direction="forwards" units="years"/>
		</taxon>
		<taxon id="H5N1|2344b|EPI_ISL_19029375|anseriformes|germany|1_1_2_1_1_1_1_1|2023-06-13">
			<date value="2023.4465753424658" direction="forwards" units="years"/>
		</taxon>
		<taxon id="H5N1|2344b|EPI_ISL_18788589|anseriformes|denmark|1_1_2_1_1_1_1_1|2022-09-12">
			<date value="2022.695890410959" direction="forwards" units="years"/>
		</taxon>
		<taxon id="H5N1|2344b|EPI_ISL_18812084|anseriformes|NA|10_6_2_1_1_1_1_1|2023-11-30">
			<date value="2023.9123287671232" direction="forwards" units="years"/>
		</taxon>
		<taxon id="H5N1|2344b|EPI_ISL_18918835|anseriformes|netherlands|1_6_2_1_1_1_1_10|2024-01-28">
			<date value="2024.0737704918033" direction="forwards" units="years"/>
		</taxon>
		<taxon id="H5N1|2344b|EPI_ISL_18824201|anseriformes|france|10_1_2_1_1_1_1_1|2024-01-07">
			<date value="2024.016393442623" direction="forwards" units="years"/>
		</taxon>
		<taxon id="H5N1|2344b|EPI_ISL_18956185|anseriformes|italy|1_1_2_1_1_1_1_7|2024-01-20">
			<date value="2024.051912568306" direction="forwards" units="years"/>
		</taxon>
		<taxon id="H5N1|2344b|EPI_ISL_18956170|anseriformes|italy|10_6_2_1_1_1_1_1|2024-02-13">
			<date value="2024.1174863387978" direction="forwards" units="years"/>
		</taxon>
		<taxon id="H5N1|2344b|EPI_ISL_19028663|accipitriformes|estonia|2_1_1_1_1_1_1_1|2021-05-16">
			<date value="2021.3698630136987" direction="forwards" units="years"/>
		</taxon>
		<taxon id="H5N1|2344b|EPI_ISL_18918831|anseriformes|netherlands|1_6_2_1_1_1_1_10|2024-01-11">
			<date value="2024.0273224043715" direction="forwards" units="years"/>
		</taxon>
		<taxon id="H5N1|2344b|EPI_ISL_18816296|anseriformes|denmark|2_1_18_1_1_1_1_1|2023-12-17">
			<date value="2023.958904109589" direction="forwards" units="years"/>
		</taxon>
		<taxon id="H5N1|2344b|EPI_ISL_18816295|anseriformes|denmark|2_1_2_1_1_1_1_1|2023-12-05">
			<date value="2023.9260273972602" direction="forwards" units="years"/>
		</taxon>
		<taxon id="H5N1|2344b|EPI_ISL_18816294|anseriformes|denmark|1_6_2_1_1_1_1_10|2023-12-11">
			<date value="2023.9424657534246" direction="forwards" units="years"/>
		</taxon>
		<taxon id="H5N1|2344b|EPI_ISL_18815361|anseriformes|sweden|2_1_2_1_1_1_1_1|2024-01-01">
			<date value="2024.0" direction="forwards" units="years"/>
		</taxon>
		<taxon id="H5N1|2344b|EPI_ISL_18815329|anseriformes|sweden|1_1_2_1_1_1_1_1|2024-01-11">
			<date value="2024.0273224043715" direction="forwards" units="years"/>
		</taxon>
		<taxon id="H5N1|2344b|EPI_ISL_18789928|anseriformes|sweden|10_1_2_1_1_1_1_1|2023-12-18">
			<date value="2023.9616438356165" direction="forwards" units="years"/>
		</taxon>
		<taxon id="H5N1|2344b|EPI_ISL_18787920|anseriformes|sweden|1_6_2_1_1_1_1_1|2023-12-07">
			<date value="2023.9315068493152" direction="forwards" units="years"/>
		</taxon>
		<taxon id="H5N1|2344b|EPI_ISL_18885828|galliformes|poland|10_1_2_1_1_1_1_1|2024-01-27">
			<date value="2024.0710382513662" direction="forwards" units="years"/>
		</taxon>
		<taxon id="H5N1|2344b|EPI_ISL_18918809|anseriformes|netherlands|1_6_2_1_1_1_1_10|2024-01-10">
			<date value="2024.0245901639344" direction="forwards" units="years"/>
		</taxon>
		<taxon id="H5N1|2344b|EPI_ISL_18953064|galliformes|denmark|1_6_2_1_1_1_1_10|2024-01-26">
			<date value="2024.068306010929" direction="forwards" units="years"/>
		</taxon>
		<taxon id="H5N1|2344b|EPI_ISL_18824185|galliformes|france|1_6_2_1_1_1_1_1|2024-01-10">
			<date value="2024.0245901639344" direction="forwards" units="years"/>
		</taxon>
		<taxon id="H5N1|2344b|EPI_ISL_15038826|galliformes|united_kingdom|1_1_4_1_4_1_1_4|2022-08-31">
			<date value="2022.66301369863" direction="forwards" units="years"/>
		</taxon>
		<taxon id="H5N1|2344b|EPI_ISL_15038821|galliformes|united_kingdom|1_1_4_1_4_1_1_4|2022-09-04">
			<date value="2022.6739726027397" direction="forwards" units="years"/>
		</taxon>
		<taxon id="H5N1|2344b|EPI_ISL_15957991|galliformes|united_kingdom|1_1_2_1_1_1_1_1|2022-11-14">
			<date value="2022.868493150685" direction="forwards" units="years"/>
		</taxon>
		<taxon id="H5N1|2344b|EPI_ISL_9616217|accipitriformes|netherlands|NA|2022-01-06">
			<date value="2022.013698630137" direction="forwards" units="years"/>
		</taxon>
		<taxon id="H5N1|2344b|EPI_ISL_17637991|carnivora|united_kingdom|NA|2022-01-24">
			<date value="2022.0630136986301" direction="forwards" units="years"/>
		</taxon>
		<taxon id="H5N1|2344b|EPI_ISL_9649405|anseriformes|sweden|NA|2021-12-17">
			<date value="2021.958904109589" direction="forwards" units="years"/>
		</taxon>
		<taxon id="H5N1|2344b|EPI_ISL_14751463|charadriiformes|netherlands|NA|2022-07-14">
			<date value="2022.531506849315" direction="forwards" units="years"/>
		</taxon>
		<taxon id="H5N1|2344b|EPI_ISL_15585919|galliformes|united_kingdom|NA|2022-10-17">
			<date value="2022.7917808219179" direction="forwards" units="years"/>
		</taxon>
		<taxon id="H5N1|2344b|EPI_ISL_15676638|anseriformes|croatia|NA|2022-10-18">
			<date value="2022.7945205479452" direction="forwards" units="years"/>
		</taxon>
		<taxon id="H5N1|2344b|EPI_ISL_16979811|anseriformes|italy|NA|2022-11-29">
			<date value="2022.9095890410958" direction="forwards" units="years"/>
		</taxon>
		<taxon id="H5N1|2344b|EPI_ISL_16122152|anseriformes|germany|NA|2022-07-21">
			<date value="2022.5506849315068" direction="forwards" units="years"/>
		</taxon>
		<taxon id="H5N1|2344b|EPI_ISL_13658359|falconiformes|israel|NA|2022-01-02">
			<date value="2022.0027397260274" direction="forwards" units="years"/>
		</taxon>
		<taxon id="H5N1|2344b|EPI_ISL_17394087|accipitriformes|canada|6_4_1_1_2_1_1_1|2022-04-26">
			<date value="2022.3150684931506" direction="forwards" units="years"/>
		</taxon>
		<taxon id="H6N1|2344b|EPI_ISL_9956393|environment|bangladesh|NA|2021-01-10">
			<date value="2021.0246575342467" direction="forwards" units="years"/>
		</taxon>
		<taxon id="H6N1|2344b|EPI_ISL_9955427|anseriformes|bangladesh|NA|2021-01-10">
			<date value="2021.0246575342467" direction="forwards" units="years"/>
		</taxon>
		<taxon id="H5N1|2344b|EPI_ISL_18285996|anseriformes|netherlands|NA|2023-08-30">
			<date value="2023.6602739726027" direction="forwards" units="years"/>
		</taxon>
		<taxon id="H5N1|2344b|EPI_ISL_819124|anseriformes|netherlands|NA|2019-01-23">
			<date value="2019.0602739726028" direction="forwards" units="years"/>
		</taxon>
		<taxon id="H1N1|2344b|EPI_ISL_16749077|anseriformes|belgium|NA|2022-08-03">
			<date value="2022.5863013698631" direction="forwards" units="years"/>
		</taxon>
		<taxon id="H6N1|2344b|EPI_ISL_328971|anseriformes|united_states|NA|2015-10-10">
			<date value="2015.772602739726" direction="forwards" units="years"/>
		</taxon>
		<taxon id="H5N1|2344b|EPI_ISL_18107049|anseriformes|united_states|2_1_1_1_1_1_1_1|2022-01-31">
			<date value="2022.0821917808219" direction="forwards" units="years"/>
		</taxon>
		<taxon id="H5N1|2344b|EPI_ISL_15081424|anseriformes|russia|NA|2021-09-17">
			<date value="2021.7095890410958" direction="forwards" units="years"/>
		</taxon>
		<taxon id="H5N1|2344b|EPI_ISL_14571443|anseriformes|germany|NA|2021-10-30">
			<date value="2021.827397260274" direction="forwards" units="years"/>
		</taxon>
		<taxon id="H5N1|2344b|EPI_ISL_18127710|NA|gambia|1_1_4_1_4_1_1_4|2023-04-01">
			<date value="2023.2465753424658" direction="forwards" units="years"/>
		</taxon>
		<taxon id="H5N1|2344b|EPI_ISL_17985196|carnivora|poland|NA|2023-06-19">
			<date value="2023.4630136986302" direction="forwards" units="years"/>
		</taxon>
	</taxa>



	<!-- The sequence alignment (each sequence refers to a taxon above).         -->
	<!-- ntax=145 nchar=1704                                                     -->
	<!-- ntax=484 nchar=1410                                                      -->
	


	<!-- The unique patterns for codon positions 1 & 2                           -->
	<mergePatterns id="CP1+2.patterns">

		<!-- The unique patterns from 1 to end every 3                               -->
		<!-- npatterns=24                                                            -->
		<patterns from="1" every="3" strip="false">
			<alignment idref="alignment"/>
		</patterns>

		<!-- The unique patterns from 2 to end every 3                               -->
		<!-- npatterns=30                                                            -->
		<patterns from="2" every="3" strip="false">
			<alignment idref="alignment"/>
		</patterns>
	</mergePatterns>

	<!-- The unique patterns for codon position 3                                -->

	<!-- The unique patterns from 3 to end every 3                               -->
	<!-- npatterns=74                                                            -->
	<patterns id="CP3.patterns" from="3" every="3" strip="false">
		<alignment idref="alignment"/>
	</patterns>


	<!-- This is a simple constant population size coalescent model              -->
	<!-- that is used to generate an initial tree for the chain.                 -->
	<constantSize id="initialDemo" units="years">
		<populationSize>
			<parameter id="initialDemo.popSize" value="100.0"/>
		</populationSize>
	</constantSize>


	<!-- Generate a random starting tree under the coalescent process            -->
	<coalescentSimulator id="startingTree">
		<taxa idref="taxa"/>
		<constantSize idref="initialDemo"/>
	</coalescentSimulator>


	<!-- Generate a tree model                                                   -->
	<treeModel id="treeModel">
		<coalescentTree idref="startingTree"/>
		<rootHeight>
			<parameter id="treeModel.rootHeight"/>
		</rootHeight>
		<nodeHeights internalNodes="true">
			<parameter id="treeModel.internalNodeHeights"/>
		</nodeHeights>
		<nodeHeights internalNodes="true" rootNode="true">
			<parameter id="treeModel.allInternalNodeHeights"/>
		</nodeHeights>
	</treeModel>

	<!-- Statistic for sum of the branch lengths of the tree (tree length)       -->
	<treeLengthStatistic id="treeLength">
		<treeModel idref="treeModel"/>
	</treeLengthStatistic>

	<!-- Statistic for time of most recent common ancestor of tree               -->
	<tmrcaStatistic id="age(root)" absolute="true">
		<treeModel idref="treeModel"/>
	</tmrcaStatistic>



	<!-- Generate a gmrfSkyGridLikelihood for the Bayesian SkyGrid process       -->
	<gmrfSkyGridLikelihood id="skygrid">
		<populationSizes>

			<!-- skygrid.logPopSize is in log units unlike other popSize                 -->
			<parameter id="skygrid.logPopSize" dimension="36" value="1.0"/>
		</populationSizes>
		<precisionParameter>
			<parameter id="skygrid.precision" value="0.1" lower="0.0"/>
		</precisionParameter>
		<numGridPoints>
			<parameter id="skygrid.numGridPoints" value="35.0"/>
		</numGridPoints>
		<cutOff>
			<parameter id="skygrid.cutOff" value="9.0"/>
		</cutOff>
		<populationTree>
			<treeModel idref="treeModel"/>
		</populationTree>
	</gmrfSkyGridLikelihood>

	<!-- The uncorrelated relaxed clock (Drummond, Ho, Phillips & Rambaut (2006) PLoS Biology 4, e88 )-->
	<discretizedBranchRates id="branchRates">
		<treeModel idref="treeModel"/>
		<distribution>
			<logNormalDistributionModel meanInRealSpace="true">
				<mean>
					<parameter id="ucld.mean" value="0.005" lower="0.0"/>
				</mean>
				<stdev>
					<parameter id="ucld.stdev" value="0.3333333333333333" lower="0.0"/>
				</stdev>
			</logNormalDistributionModel>
		</distribution>
		<rateCategories>
			<parameter id="branchRates.categories"/>
		</rateCategories>
	</discretizedBranchRates>

	<rateStatistic id="meanRate" name="meanRate" mode="mean" internal="true" external="true">
		<treeModel idref="treeModel"/>
		<discretizedBranchRates idref="branchRates"/>
	</rateStatistic>

	<rateStatistic id="coefficientOfVariation" name="coefficientOfVariation" mode="coefficientOfVariation" internal="true" external="true">
		<treeModel idref="treeModel"/>
		<discretizedBranchRates idref="branchRates"/>
	</rateStatistic>

	<rateCovarianceStatistic id="covariance" name="covariance">
		<treeModel idref="treeModel"/>
		<discretizedBranchRates idref="branchRates"/>
	</rateCovarianceStatistic>


	<!-- The HKY substitution model (Hasegawa, Kishino & Yano, 1985)             -->
	<HKYModel id="CP1+2.hky">
		<frequencies>
			<frequencyModel dataType="nucleotide">
				<frequencies>
					<parameter id="frequencies" value="0.25 0.25 0.25 0.25"/>
				</frequencies>
			</frequencyModel>
		</frequencies>
		<kappa>
			<parameter id="CP1+2.kappa" value="2.0" lower="0.0"/>
		</kappa>
	</HKYModel>

	<!-- The HKY substitution model (Hasegawa, Kishino & Yano, 1985)             -->
	<HKYModel id="CP3.hky">
		<frequencies>
			<frequencyModel dataType="nucleotide">
				<frequencies>
					<parameter idref="frequencies"/>
				</frequencies>
			</frequencyModel>
		</frequencies>
		<kappa>
			<parameter id="CP3.kappa" value="2.0" lower="0.0"/>
		</kappa>
	</HKYModel>

	<!-- site model                                                              -->
	<siteModel id="CP1+2.siteModel">
		<substitutionModel>
			<HKYModel idref="CP1+2.hky"/>
		</substitutionModel>
		<relativeRate>
			<parameter id="CP1+2.mu" value="1.0" lower="0.0"/>
		</relativeRate>
		<gammaShape gammaCategories="4">
			<parameter id="CP1+2.alpha" value="0.5" lower="0.0"/>
		</gammaShape>
	</siteModel>

	<!-- site model                                                              -->
	<siteModel id="CP3.siteModel">
		<substitutionModel>
			<HKYModel idref="CP3.hky"/>
		</substitutionModel>
		<relativeRate>
			<parameter id="CP3.mu" value="1.0" lower="0.0"/>
		</relativeRate>
		<gammaShape gammaCategories="4">
			<parameter id="CP3.alpha" value="0.5" lower="0.0"/>
		</gammaShape>
	</siteModel>



	<!-- Collecting together relative rates for partitions                       -->
	<compoundParameter id="allMus">
		<parameter idref="CP1+2.mu"/>
		<parameter idref="CP3.mu"/>
	</compoundParameter>


	<!-- Likelihood for tree given sequence data                                 -->
	<treeDataLikelihood id="treeLikelihood" useAmbiguities="false">
		<partition>
			<mergePatterns idref="CP1+2.patterns"/>
			<siteModel idref="CP1+2.siteModel"/>
		</partition>
		<partition>
			<patterns idref="CP3.patterns"/>
			<siteModel idref="CP3.siteModel"/>
		</partition>
		<treeModel idref="treeModel"/>
		<discretizedBranchRates idref="branchRates"/>
	</treeDataLikelihood>


	<!-- Define operators                                                        -->
	<operators id="operators" optimizationSchedule="log">
		<scaleOperator scaleFactor="0.75" weight="1">
			<parameter idref="CP1+2.kappa"/>
		</scaleOperator>
		<scaleOperator scaleFactor="0.75" weight="1">
			<parameter idref="CP3.kappa"/>
		</scaleOperator>
		<deltaExchange delta="0.01" weight="1">
			<parameter idref="frequencies"/>
		</deltaExchange>
		<scaleOperator scaleFactor="0.75" weight="1">
			<parameter idref="CP1+2.alpha"/>
		</scaleOperator>
		<scaleOperator scaleFactor="0.75" weight="1">
			<parameter idref="CP3.alpha"/>
		</scaleOperator>
		<scaleOperator scaleFactor="0.75" weight="3">
			<parameter idref="ucld.mean"/>
		</scaleOperator>
		<scaleOperator scaleFactor="0.75" weight="3">
			<parameter idref="ucld.stdev"/>
		</scaleOperator>
		<upDownOperator scaleFactor="0.75" weight="3">
			<up>
				<parameter idref="treeModel.allInternalNodeHeights"/>
			</up>
			<down>
				<parameter idref="ucld.mean"/>
			</down>
		</upDownOperator>
		<swapOperator size="1" weight="10" autoOptimize="false">
			<parameter idref="branchRates.categories"/>
		</swapOperator>
		<uniformIntegerOperator weight="10">
			<parameter idref="branchRates.categories"/>
		</uniformIntegerOperator>
		<deltaExchange delta="0.01" parameterWeights="1136 568" weight="3">
			<parameter idref="allMus"/>
		</deltaExchange>
		<subtreeSlide size="1.0" gaussian="true" weight="30">
			<treeModel idref="treeModel"/>
		</subtreeSlide>
		<narrowExchange weight="30">
			<treeModel idref="treeModel"/>
		</narrowExchange>
		<wideExchange weight="3">
			<treeModel idref="treeModel"/>
		</wideExchange>
		<wilsonBalding weight="3">
			<treeModel idref="treeModel"/>
		</wilsonBalding>
		<scaleOperator scaleFactor="0.75" weight="3">
			<parameter idref="treeModel.rootHeight"/>
		</scaleOperator>
		<uniformOperator weight="30">
			<parameter idref="treeModel.internalNodeHeights"/>
		</uniformOperator>
		<gmrfGridBlockUpdateOperator scaleFactor="1.0" weight="2">
			<gmrfSkyrideLikelihood idref="skygrid"/>
		</gmrfGridBlockUpdateOperator>
		<scaleOperator scaleFactor="0.75" weight="1">
			<parameter idref="skygrid.precision"/>
		</scaleOperator>
	</operators>


	<!-- Define MCMC                                                             -->
	<mcmc id="mcmc" chainLength="200000000" autoOptimize="true" operatorAnalysis="n1_europe_subsampled.ops">
		<joint id="joint">
			<prior id="prior">
				<logNormalPrior mu="1.0" sigma="1.25" offset="0.0">
					<parameter idref="CP1+2.kappa"/>
				</logNormalPrior>
				<logNormalPrior mu="1.0" sigma="1.25" offset="0.0">
					<parameter idref="CP3.kappa"/>
				</logNormalPrior>
				<dirichletPrior alpha="1.0" sumsTo="1.0">
					<parameter idref="frequencies"/>
				</dirichletPrior>
				<exponentialPrior mean="0.5" offset="0.0">
					<parameter idref="CP1+2.alpha"/>
				</exponentialPrior>
				<exponentialPrior mean="0.5" offset="0.0">
					<parameter idref="CP3.alpha"/>
				</exponentialPrior>
				<uniformPrior lower="0.0" upper="100.0">
					<parameter idref="allMus"/>
				</uniformPrior>
				<trancated lower="0.0" upper="0.025">
					<logNormalPrior mean="0.005" stdev="0.005" offset="0.0">
						<parameter idref="ucld.mean"/>
					</logNormalPrior>
				</trancated>
				<exponentialPrior mean="0.3333333333333333" offset="0.0">
					<parameter idref="ucld.stdev"/>
				</exponentialPrior>
				<gammaPrior shape="0.001" scale="1000.0" offset="0.0">
					<parameter idref="skygrid.precision"/>
				</gammaPrior>

				<gmrfSkyGridLikelihood idref="skygrid"/>

				<discretizedBranchRates idref="branchRates"/>
			</prior>
			<likelihood id="likelihood">
				<treeDataLikelihood idref="treeLikelihood"/>
			</likelihood>
		</joint>
		<operators idref="operators"/>

		<!-- write log to screen                                                     -->
		<log id="screenLog" logEvery="10000">
			<column label="Joint" dp="4" width="12">
				<joint idref="joint"/>
			</column>
			<column label="Prior" dp="4" width="12">
				<prior idref="prior"/>
			</column>
			<column label="Likelihood" dp="4" width="12">
				<likelihood idref="likelihood"/>
			</column>
			<column label="age(root)" sf="6" width="12">
				<tmrcaStatistic idref="age(root)"/>
			</column>
			<column label="ucld.mean" sf="6" width="12">
				<parameter idref="ucld.mean"/>
			</column>
		</log>

		<!-- write log to file                                                       -->
		<log id="fileLog" logEvery="20000" fileName="n1_europe_subsampled_relaxLn_Skygrid9-36_2.log" overwrite="false">
			<joint idref="joint"/>
			<prior idref="prior"/>
			<likelihood idref="likelihood"/>
			<parameter idref="treeModel.rootHeight"/>
			<tmrcaStatistic idref="age(root)"/>
			<treeLengthStatistic idref="treeLength"/>
			<parameter idref="skygrid.precision"/>
			<parameter idref="skygrid.logPopSize"/>
			<parameter idref="skygrid.cutOff"/>
			<parameter idref="CP1+2.kappa"/>
			<parameter idref="CP3.kappa"/>
			<parameter idref="frequencies"/>
			<parameter idref="CP1+2.alpha"/>
			<parameter idref="CP3.alpha"/>
			<compoundParameter idref="allMus"/>
			<parameter idref="ucld.mean"/>
			<parameter idref="ucld.stdev"/>
			<rateStatistic idref="meanRate"/>
			<rateStatistic idref="coefficientOfVariation"/>
			<rateCovarianceStatistic idref="covariance"/>
			<treeDataLikelihood idref="treeLikelihood"/>
			<discretizedBranchRates idref="branchRates"/>
			<gmrfSkyGridLikelihood idref="skygrid"/>
		</log>

		<!-- write tree log to file                                                  -->
		<logTree id="treeFileLog" logEvery="20000" nexusFormat="true" fileName="n1_europe_subsampled_relaxLn_Skygrid9-36_2.trees" sortTranslationTable="true">
			<treeModel idref="treeModel"/>
			<trait name="rate" tag="rate">
				<discretizedBranchRates idref="branchRates"/>
			</trait>
			<joint idref="joint"/>
		</logTree>
	</mcmc>

	<report>
		<property name="timer">
			<mcmc idref="mcmc"/>
		</property>
	</report>

</beast>
